Workbook
Name Apartments_Abatement: Assumptions!$C$28
Name Apartments_Abatement_A: Assumptions!$C$37
Name Apartments_Base_Val: Assumptions!$B$7
Name Apartments_CDC: Assumptions!$E$28
Name Apartments_CDC_A: Assumptions!$E$37
Name Apartments_Impvt_Val: Assumptions!$B$10
Name Apartments_Land_Growth: Assumptions!$B$9
Name Apartments_Non_abated: Assumptions!$D$28
Name Apartments_Non_abated_A: Assumptions!$D$37
Name Apartments_Retained: Assumptions!$F$28
Name Apartments_Retained_A: Assumptions!$F$37
Name Apartments_Term: Assumptions!$B$28
Name Apartments_Term_A: Assumptions!$B$37
Name Condos_Base_Val: Assumptions!$D$18
Name Condos_Impvt_Val: Assumptions!$D$21
Name Condos_Land_Growth: Assumptions!$D$20
Name Full_Comm_Rate_A: Assumptions!$K$28
Name Full_Comm_Rate_B: Assumptions!$K$32
Name Full_Res_Rate_A: Assumptions!$J$28
Name Full_Res_Rate_B: Assumptions!$J$32
Name Hilliard_Abatement: Assumptions!$A$26:$F$33
Name Hilliard_Abatement_C: Assumptions!$A$26:$A$33
Name Hilliard_Abatement_R: Assumptions!$A$26:$F$26
Name Hilliard_Rates: Assumptions!$I$25:$K$28
Name Hotel_Abatement: Assumptions!$C$33
Name Hotel_Abatement_A: Assumptions!$C$42
Name Hotel_CDC: Assumptions!$E$33
Name Hotel_CDC_A: Assumptions!$E$42
Name Hotel_Non_abated: Assumptions!$D$33
Name Hotel_Non_abated_A: Assumptions!$D$42
Name Hotel_Retained: Assumptions!$F$33
Name Hotel_Retained_A: Assumptions!$F$42
Name Hotel_Term: Assumptions!$B$33
Name Hotel_Term_A: Assumptions!$B$42
Name Land_Growth_Abatement: Assumptions!$C$27
Name Land_Growth_Abatement_A: Assumptions!$C$36
Name Land_Growth_CDC: Assumptions!$E$27
Name Land_Growth_CDC_A: Assumptions!$E$36
Name Land_Growth_Non_abated: Assumptions!$D$27
Name Land_Growth_Non_abated_A: Assumptions!$D$36
Name Land_Growth_Retained: Assumptions!$F$27
Name Land_Growth_Retained_A: Assumptions!$F$36
Name Land_Growth_Term: Assumptions!$B$27
Name Land_Growth_Term_A: Assumptions!$B$36
Name Non_School_Comm_Rate_A: Assumptions!$K$27
Name Non_School_Comm_Rate_B: Assumptions!$K$31
Name Non_School_Res_Rate_A: Assumptions!$J$27
Name Non_School_Res_Rate_B: Assumptions!$J$31
Name Office_Abatement: Assumptions!$C$30
Name Office_Abatement_A: Assumptions!$C$39
Name Office_Base_Val: Assumptions!$B$18
Name Office_CDC: Assumptions!$E$30
Name Office_CDC_A: Assumptions!$E$39
Name Office_Impvt_Val: Assumptions!$B$21
Name Office_Land_Growth: Assumptions!$B$20
Name Office_Non_abated: Assumptions!$D$30
Name Office_Non_abated_A: Assumptions!$D$39
Name Office_Retained: Assumptions!$F$30
Name Office_Retained_A: Assumptions!$F$39
Name Office_Term: Assumptions!$B$30

Sheet Assumptions
A1: Development Composition | E1: BOND ASSUMPTIONS AND REVENUE SUMMARY
A2: Apartments | C2: Single-Family Homes | E2: A Bond
A3: Completion | B3: 2022 | C3: Completion | D3: 2023 | E3: NPV | F3: 0.0325 | G3: =NPV(F3,'Revenue Summary'!B16:AE16) -> 16381326
A4: Acreage | B4: 10.38 | C4: Acreage | D4: 4.28 | E4: Cap int | F4: 0.05 | G4: =-G3*F4 -> -819066.32
A5: Units or SF | B5: 293 | C5: Units or SF | D5: 12 | E5: Issuance | F5: 0.04 | G5: =-G3*F5 -> -655253.05
A6: Value per unit | B6: 132000 | C6: Value per unit | D6: 750000 | E6: Reserve | F6: 0.1 | G6: =G3*F6*-1 -> -1638132.6
A7: Base Value | B7: =H28*B4 -> 869325 | C7: Base Value | D7: =H28*D4 -> 358450 | E7: Total | G7: =SUM(G3:G6) -> 13268874
A8: Prelim. Impvmt Value | B8: =B5*B6-B7 -> 37806675 | C8: Prelim. Impvmt Value | D8: =D5*D6-D7 -> 8641550
A9: Land Growth | B9: =$H$30*B8 -> 4536801 | C9: Land Growth | D9: =$H$30*D8 -> 1036986 | E9: Surplus
A10: Improvement Value | B10: =B8-B9 -> 33269874 | C10: Improvement Value | D10: =D8-D9 -> 7604564 | E10: Rate | F10: 0.09 | G10: =NPV(F3,'Revenue Summary'!B19:AE19) -> 1638132.6
A11: Total Value | B11: =SUM(B7,B9,B10) -> 38676000 | C11: Total Value | D11: =SUM(D7,D9,D10) -> 9000000 | E11: Issuance | F11: =F4 -> 0.05 | G11: =-G10*F11 -> -81906.632
E12: Cap int | F12: =F5 -> 0.04 | G12: =-G10*F12 -> -65525.305
A13: Office | C13: Condos | E13: Reserve | F13: =F6 -> 0.1 | G13: =G10*F13*-1 -> -163813.26
A14: Completion | B14: 2022 | C14: Completion | D14: 2023 | E14: Total | G14: =SUM(G10:G13) -> 1326887.4
A15: Acreage | B15: 1.67 | C15: Acreage | D15: 1.0585714 | E15: DEBT COVERAGE RATIO
A16: Units or SF | B16: 43000 | C16: Units or SF | D16: 31 | E16: Ratio | G16: 1.1
A17: Value per unit | B17: 160 | C17: Value per unit | D17: 550000 | E17: Revenue
A18: Base Value | B18: =H28*B15 -> 139862.5 | C18: Base Value | D18: =H28*D15 -> 88655.357 | F18: A Bonds | G18: Surplus
A19: Prelim. Impvmt Value | B19: =B16*B17-B18 -> 6740137.5 | C19: Prelim. Impvmt Value | D19: =D16*D17-D18 -> 16961345 | E19: Gross Revenue Bond Sale | F19: =G3 -> 16381326 | G19: =G10 -> 1638132.6
A20: Land Growth | B20: =$H$30*B19 -> 808816.5 | C20: Land Growth | D20: =$H$30*D19 -> 2035361.4 | E20: Net Rev NCA | F20: =G7 -> 13268874 | G20: =G14 -> 1326887.4
A21: Improvement Value | B21: =B19-B20 -> 5931321 | C21: Improvement Value | D21: =D19-D20 -> 14925983
A22: Total Value | B22: =SUM(B18,B20,B21) -> 6880000 | C22: Total Value | D22: =SUM(D18,D20,D21) -> 17050000 | E22: Total revenue to NCA | F22: =G7+G14 -> 14595762 | G22: =F22/$F$22 -> 1
A25: Abatement Structure | B25: Municipality A | G25: Development Base Value Details | I25: Municipality A, Tax Rates | J25: Residential | K25: Commercial
A26: Use | B26: Term (years) | C26: Abatement | D26: Non-abated | E26: CDC | F26: Retained | G26: Total acres | H26: 80 | I26: School | J26: 0.057772736 | K26: 0.066633322
A27: Land Growth | B27: 10 | C27: 1 | D27: =1-C27 -> 0 | E27: 0.5 | F27: =IF((C27-D27-E27)<0,0,(C27-D27-E27)) -> 0.5 | G27: Base value | H27: 6700000 | I27: Non-school | J27: 0.022720332 | K27: 0.023702183
A28: Apartments | B28: 15 | C28: 1 | D28: =1-C28 -> 0 | E28: 0.5 | F28: =IF((C28-E28)<0,0,(C28-E28)) -> 0.5 | G28: Base per acre | H28: =H27/H26 -> 83750 | I28: Total | J28: =SUM(J26:J27) -> 0.080493068 | K28: =SUM(K26:K27) -> 0.090335505
A29: For Sale Residential | B29: 15 | C29: 1 | D29: =1-C29 -> 0 | E29: 0.5 | F29: =IF((C29-E29)<0,0,(C29-E29)) -> 0.5 | I29: Municipality B, Tax Rates | J29: Residential | K29: Commercial
A30: Office | B30: 10 | C30: 0.75 | D30: =1-C30 -> 0.25 | E30: 0.25 | F30: =IF((C30-E30)<0,0,(C30-E30)) -> 0.5 | G30: Land growth factor | H30: 0.12 | I30: School | J30: 0 | K30: 0
A31: Retail | B31: 0 | C31: 0 | D31: =1-C31 -> 1 | E31: 0 | F31: =IF((C31-E31)<0,0,(C31-E31)) -> 0 | I31: Non-school | J31: 0 | K31: 0
A32: Senior Apartments | B32: 15 | C32: 1 | D32: =1-C32 -> 0 | E32: 0.5 | F32: =IF((C32-E32)<0,0,(C32-E32)) -> 0.5 | I32: Total | J32: =SUM(J30:J31) -> 0 | K32: =SUM(K30:K31) -> 0
A33: Hotel | B33: 0 | C33: 0 | D33: =1-C33 -> 1 | E33: 0 | F33: =IF((C33-E33)<0,0,(C33-E33)) -> 0
A34: Abatement Structure | B34: Municipality B | G34: Minor Re-Appraisal | H34: 0.03
A35: Use | B35: Term (years) | C35: Abatement | D35: Non-abated | E35: CDC | F35: Retained | G35: Major Re-Appraisal | H35: 0.06
A36: Land Growth | B36: 10 | C36: 1 | D36: =1-C36 -> 0 | E36: 0.5 | F36: =IF((C36-D36-E36)<0,0,(C36-D36-E36)) -> 0.5
A37: Apartments | B37: 15 | C37: 1 | D37: =1-C37 -> 0 | E37: 0.5 | F37: =IF((C37-E37)<0,0,(C37-E37)) -> 0.5
A38: For Sale Residential | B38: 15 | C38: 1 | D38: =1-C38 -> 0 | E38: 0.5 | F38: =IF((C38-E38)<0,0,(C38-E38)) -> 0.5
A39: Office | B39: 10 | C39: 0.75 | D39: =1-C39 -> 0.25 | E39: 0.25 | F39: =IF((C39-E39)<0,0,(C39-E39)) -> 0.5
A40: Retail | B40: 0 | C40: 0 | D40: =1-C40 -> 1 | E40: 0 | F40: =IF((C40-E40)<0,0,(C40-E40)) -> 0
A41: Senior Apartments | B41: 15 | C41: 1 | D41: =1-C41 -> 0 | E41: 0.5 | F41: =IF((C41-E41)<0,0,(C41-E41)) -> 0.5
A42: Hotel | B42: 0 | C42: 0 | D42: =1-C42 -> 1 | E42: 0 | F42: =IF((C42-E42)<0,0,(C42-E42)) -> 0

Sheet Calculations
A1: Tax Year | B1: 2020 | C1: =B1+1 -> 2021 | D1: =C1+1 -> 2022 | E1: =D1+1 -> 2023 | F1: =E1+1 -> 2024 | G1: =F1+1 -> 2025 | H1: =G1+1 -> 2026 | I1: =H1+1 -> 2027 | J1: =I1+1 -> 2028 | ... AE1: =AD1+1 -> 2049
A2: Collection Year | B2: =B1+1 -> 2021 | C2: =C1+1 -> 2022 | D2: =D1+1 -> 2023 | E2: =E1+1 -> 2024 | F2: =F1+1 -> 2025 | G2: =G1+1 -> 2026 | H2: =H1+1 -> 2027 | I2: =I1+1 -> 2028 | ... AE2: =AE1+1 -> 2050
A3: Inflation factor | B3: =Assumptions!$H$34 -> 0.03 | C3: 0 | D3: 0 | E3: =Assumptions!$H$35 -> 0.06 | F3: 0 | G3: 0 | H3: =B3 -> 0.03 | I3: 0 | J3: 0 | K3: =E3 -> 0.06 | L3: 0 | M3: 0 | N3: =H3 -> 0.03 | O3: 0 | P3: 0 | Q3: =K3 -> 0.06 | R3: 0 | S3: 0 | T3: =N3 -> 0.03 | U3: 0 | V3: 0 | W3: =Q3 -> 0.06 | X3: 0 | Y3: 0 | Z3: =T3 -> 0.03 | AA3: 0 | AB3: 0 | AC3: =W3 -> 0.06 | AD3: 0 | AE3: 0
A4: Cumulative inflation | B4: =SUM($B$3:B3) -> 0.03 | C4: =B4 -> 0.03 | D4: =B4 -> 0.03 | E4: =((1+B4)*(1+E3))-1 -> 0.0918 | F4: =E4 -> 0.0918 | G4: =E4 -> 0.0918 | H4: =((1+E4)*(1+H3))-1 -> 0.124554 | I4: =H4 -> 0.124554 | J4: =H4 -> 0.124554 | K4: =((1+H4)*(1+K3))-1 -> 0.19202724 | L4: =K4 -> 0.19202724 | M4: =K4 -> 0.19202724 | N4: =((1+K4)*(1+N3))-1 -> 0.22778806 | O4: =N4 -> 0.22778806 | P4: =N4 -> 0.22778806 | Q4: =((1+N4)*(1+Q3))-1 -> 0.30145534 | R4: =Q4 -> 0.30145534 | S4: =Q4 -> 0.30145534 | T4: =((1+Q4)*(1+T3))-1 -> 0.340499 | U4: =T4 -> 0.340499 | V4: =T4 -> 0.340499 | W4: =((1+T4)*(1+W3))-1 -> 0.42092894 | X4: =W4 -> 0.42092894 | Y4: =W4 -> 0.42092894 | Z4: =((1+W4)*(1+Z3))-1 -> 0.46355681 | AA4: =Z4 -> 0.46355681 | AB4: =Z4 -> 0.46355681 | AC4: =((1+Z4)*(1+AC3))-1 -> 0.55137022 | AD4: =AC4 -> 0.55137022 | AE4: =AC4 -> 0.55137022
A6: =Assumptions!$A$2 -> Apartments
A7: Land abatement year | B7: =IF(Land_Growth_Term>0,1) -> 1 | C7: =IF(Land_Growth_Term>0,B7+1) -> 2 | D7: =IF(Land_Growth_Term>0,C7+1) -> 3 | E7: =IF(Land_Growth_Term>0,D7+1) -> 4 | F7: =IF(Land_Growth_Term>0,E7+1) -> 5 | G7: =IF(Land_Growth_Term>0,F7+1) -> 6 | H7: =IF(Land_Growth_Term>0,G7+1) -> 7 | I7: =IF(Land_Growth_Term>0,H7+1) -> 8 | J7: =IF(Land_Growth_Term>0,I7+1) -> 9 | K7: =IF(Land_Growth_Term>0,J7+1) -> 10
A8: Building abatement year | B8: =IF(Assumptions!$B$3>=B$2,0,IF(Assumptions!$B$3+1=B$2,1,IF(Assumptions!$B$3+15>=B$2,A8+1,0))) -> 0 | C8: =IF(Assumptions!$B$3>=C$2,0,IF(Assumptions!$B$3+1=C$2,1,IF(Assumptions!$B$3+15>=C$2,B8+1,0))) -> 0 | D8: =IF(Assumptions!$B$3>=D$2,0,IF(Assumptions!$B$3+1=D$2,1,IF(Assumptions!$B$3+15>=D$2,C8+1,0))) -> 1 | E8: =IF(Assumptions!$B$3>=E$2,0,IF(Assumptions!$B$3+1=E$2,1,IF(Assumptions!$B$3+15>=E$2,D8+1,0))) -> 2 | F8: =IF(Assumptions!$B$3>=F$2,0,IF(Assumptions!$B$3+1=F$2,1,IF(Assumptions!$B$3+15>=F$2,E8+1,0))) -> 3 | G8: =IF(Assumptions!$B$3>=G$2,0,IF(Assumptions!$B$3+1=G$2,1,IF(Assumptions!$B$3+15>=G$2,F8+1,0))) -> 4 | H8: =IF(Assumptions!$B$3>=H$2,0,IF(Assumptions!$B$3+1=H$2,1,IF(Assumptions!$B$3+15>=H$2,G8+1,0))) -> 5 | I8: =IF(Assumptions!$B$3>=I$2,0,IF(Assumptions!$B$3+1=I$2,1,IF(Assumptions!$B$3+15>=I$2,H8+1,0))) -> 6 | ... AE8: =IF(Assumptions!$B$3>=AE$2,0,IF(Assumptions!$B$3+1=AE$2,1,IF(Assumptions!$B$3+15>=AE$2,AD8+1,0))) -> 0
A9: Base value | B9: =Apartments_Base_Val -> 869325 | C9: =B9 -> 869325 | D9: =C9 -> 869325 | E9: =D9 -> 869325 | F9: =E9 -> 869325 | G9: =F9 -> 869325 | H9: =G9 -> 869325 | I9: =H9 -> 869325 | J9: =I9 -> 869325 | ... AE9: =AD9 -> 869325
A10: Land growth | B10: =IF(B$2<=Assumptions!$B$3,0,IF(B$2=Assumptions!$B$3+1,Apartments_Land_Growth*(1+B$4),IF(B$2>Assumptions!$B$3,A10*(1+B$3),0))) -> 0 | C10: =IF(C$2<=Assumptions!$B$3,0,IF(C$2=Assumptions!$B$3+1,Apartments_Land_Growth*(1+C$4),IF(C$2>Assumptions!$B$3,B10*(1+C$3),0))) -> 0 | D10: =IF(D$2<=Assumptions!$B$3,0,IF(D$2=Assumptions!$B$3+1,Apartments_Land_Growth*(1+D$4),IF(D$2>Assumptions!$B$3,C10*(1+D$3),0))) -> 4672905 | E10: =IF(E$2<=Assumptions!$B$3,0,IF(E$2=Assumptions!$B$3+1,Apartments_Land_Growth*(1+E$4),IF(E$2>Assumptions!$B$3,D10*(1+E$3),0))) -> 4953279.3 | F10: =IF(F$2<=Assumptions!$B$3,0,IF(F$2=Assumptions!$B$3+1,Apartments_Land_Growth*(1+F$4),IF(F$2>Assumptions!$B$3,E10*(1+F$3),0))) -> 4953279.3 | G10: =IF(G$2<=Assumptions!$B$3,0,IF(G$2=Assumptions!$B$3+1,Apartments_Land_Growth*(1+G$4),IF(G$2>Assumptions!$B$3,F10*(1+G$3),0))) -> 4953279.3 | H10: =IF(H$2<=Assumptions!$B$3,0,IF(H$2=Assumptions!$B$3+1,Apartments_Land_Growth*(1+H$4),IF(H$2>Assumptions!$B$3,G10*(1+H$3),0))) -> 5101877.7 | I10: =IF(I$2<=Assumptions!$B$3,0,IF(I$2=Assumptions!$B$3+1,Apartments_Land_Growth*(1+I$4),IF(I$2>Assumptions!$B$3,H10*(1+I$3),0))) -> 5101877.7 | ... AE10: =IF(AE$2<=Assumptions!$B$3,0,IF(AE$2=Assumptions!$B$3+1,Apartments_Land_Growth*(1+AE$4),IF(AE$2>Assumptions!$B$3,AD10*(1+AE$3),0))) -> 7038258
A11: Improvement value | B11: =IF(B$2<=Assumptions!$B$3,0,IF(B$2=Assumptions!$B$3+1,Apartments_Impvt_Val*(1+B$4),IF(B$2>Assumptions!$B$3,A11*(1+B$3),0))) -> 0 | C11: =IF(C$2<=Assumptions!$B$3,0,IF(C$2=Assumptions!$B$3+1,Apartments_Impvt_Val*(1+C$4),IF(C$2>Assumptions!$B$3,B11*(1+C$3),0))) -> 0 | D11: =IF(D$2<=Assumptions!$B$3,0,IF(D$2=Assumptions!$B$3+1,Apartments_Impvt_Val*(1+D$4),IF(D$2>Assumptions!$B$3,C11*(1+D$3),0))) -> 34267970 | E11: =IF(E$2<=Assumptions!$B$3,0,IF(E$2=Assumptions!$B$3+1,Apartments_Impvt_Val*(1+E$4),IF(E$2>Assumptions!$B$3,D11*(1+E$3),0))) -> 36324048 | F11: =IF(F$2<=Assumptions!$B$3,0,IF(F$2=Assumptions!$B$3+1,Apartments_Impvt_Val*(1+F$4),IF(F$2>Assumptions!$B$3,E11*(1+F$3),0))) -> 36324048 | G11: =IF(G$2<=Assumptions!$B$3,0,IF(G$2=Assumptions!$B$3+1,Apartments_Impvt_Val*(1+G$4),IF(G$2>Assumptions!$B$3,F11*(1+G$3),0))) -> 36324048 | H11: =IF(H$2<=Assumptions!$B$3,0,IF(H$2=Assumptions!$B$3+1,Apartments_Impvt_Val*(1+H$4),IF(H$2>Assumptions!$B$3,G11*(1+H$3),0))) -> 37413770 | I11: =IF(I$2<=Assumptions!$B$3,0,IF(I$2=Assumptions!$B$3+1,Apartments_Impvt_Val*(1+I$4),IF(I$2>Assumptions!$B$3,H11*(1+I$3),0))) -> 37413770 | ... AE11: =IF(AE$2<=Assumptions!$B$3,0,IF(AE$2=Assumptions!$B$3+1,Apartments_Impvt_Val*(1+AE$4),IF(AE$2>Assumptions!$B$3,AD11*(1+AE$3),0))) -> 51613892
A12: Full Value Tax
A13: Full value | B13: =SUM(B9:B11) -> 869325 | C13: =SUM(C9:C11) -> 869325 | D13: =SUM(D9:D11) -> 39810200 | E13: =SUM(E9:E11) -> 42146653 | F13: =SUM(F9:F11) -> 42146653 | G13: =SUM(G9:G11) -> 42146653 | H13: =SUM(H9:H11) -> 43384973 | I13: =SUM(I9:I11) -> 43384973 | ... AE13: =SUM(AE9:AE11) -> 59521475
A14: Full tax | B14: =B13*0.35*Full_Comm_Rate_A -> 27485.82 | C14: =C13*0.35*Full_Comm_Rate_A -> 27485.82 | D14: =D13*0.35*Full_Comm_Rate_A -> 1258696.1 | E14: =E13*0.35*Full_Comm_Rate_A -> 1332568.7 | F14: =F13*0.35*Full_Comm_Rate_A -> 1332568.7 | G14: =G13*0.35*Full_Comm_Rate_A -> 1332568.7 | H14: =H13*0.35*Full_Comm_Rate_A -> 1371721.2 | I14: =I13*0.35*Full_Comm_Rate_A -> 1371721.2 | ... AE14: =AE13*0.35*Full_Comm_Rate_A -> 1881915.9
A15: Collection Items
A16: Tax to school | B16: =IF(AND(B7=0,B8=0),(B9*0.35*School_Comm_Rate_A)+(B10*0.35*School_Comm_Rate_A)+(B11*0.35*School_Comm_Rate_A),IF(AND(B7=0,B8>0),(B9*0.35*School_Comm_Rate_A)+(B10*0.35*School_Comm_Rate_A)+(B11*Apartments_Non_abated*0.35*School_Comm_Rate_A),IF(AND(B7>0,B8=0),(B9*0.35*School_Comm_Rate_A)+(B10*Land_Growth_Non_abated*0.35*School_Comm_Rate_A)+(B11*0.35*School_Comm_Rate_A),IF(AND(B7>0,B8>0),(B9*0.35*School_Comm_Rate_A)+(B10*Land_Growth_Non_abated*0.35*School_Comm_Rate_A)+(B11*Apartments_Non_abated*0.35*School_Comm_Rate_A),0)))) -> 20274.104 | C16: =IF(AND(C7=0,C8=0),(C9*0.35*School_Comm_Rate_A)+(C10*0.35*School_Comm_Rate_A)+(C11*0.35*School_Comm_Rate_A),IF(AND(C7=0,C8>0),(C9*0.35*School_Comm_Rate_A)+(C10*0.35*School_Comm_Rate_A)+(C11*Apartments_Non_abated*0.35*School_Comm_Rate_A),IF(AND(C7>0,C8=0),(C9*0.35*School_Comm_Rate_A)+(C10*Land_Growth_Non_abated*0.35*School_Comm_Rate_A)+(C11*0.35*School_Comm_Rate_A),IF(AND(C7>0,C8>0),(C9*0.35*School_Comm_Rate_A)+(C10*Land_Growth_Non_abated*0.35*School_Comm_Rate_A)+(C11*Apartments_Non_abated*0.35*School_Comm_Rate_A),0)))) -> 20274.104 | D16: =IF(AND(D7=0,D8=0),(D9*0.35*School_Comm_Rate_A)+(D10*0.35*School_Comm_Rate_A)+(D11*0.35*School_Comm_Rate_A),IF(AND(D7=0,D8>0),(D9*0.35*School_Comm_Rate_A)+(D10*0.35*School_Comm_Rate_A)+(D11*Apartments_Non_abated*0.35*School_Comm_Rate_A),IF(AND(D7>0,D8=0),(D9*0.35*School_Comm_Rate_A)+(D10*Land_Growth_Non_abated*0.35*School_Comm_Rate_A)+(D11*0.35*School_Comm_Rate_A),IF(AND(D7>0,D8>0),(D9*0.35*School_Comm_Rate_A)+(D10*Land_Growth_Non_abated*0.35*School_Comm_Rate_A)+(D11*Apartments_Non_abated*0.35*School_Comm_Rate_A),0)))) -> 20274.104 | E16: =IF(AND(E7=0,E8=0),(E9*0.35*School_Comm_Rate_A)+(E10*0.35*School_Comm_Rate_A)+(E11*0.35*School_Comm_Rate_A),IF(AND(E7=0,E8>0),(E9*0.35*School_Comm_Rate_A)+(E10*0.35*School_Comm_Rate_A)+(E11*Apartments_Non_abated*0.35*School_Comm_Rate_A),IF(AND(E7>0,E8=0),(E9*0.35*School_Comm_Rate_A)+(E10*Land_Growth_Non_abated*0.35*School_Comm_Rate_A)+(E11*0.35*School_Comm_Rate_A),IF(AND(E7>0,E8>0),(E9*0.35*School_Comm_Rate_A)+(E10*Land_Growth_Non_abated*0.35*School_Comm_Rate_A)+(E11*Apartments_Non_abated*0.35*School_Comm_Rate_A),0)))) -> 20274.104 | F16: =IF(AND(F7=0,F8=0),(F9*0.35*School_Comm_Rate_A)+(F10*0.35*School_Comm_Rate_A)+(F11*0.35*School_Comm_Rate_A),IF(AND(F7=0,F8>0),(F9*0.35*School_Comm_Rate_A)+(F10*0.35*School_Comm_Rate_A)+(F11*Apartments_Non_abated*0.35*School_Comm_Rate_A),IF(AND(F7>0,F8=0),(F9*0.35*School_Comm_Rate_A)+(F10*Land_Growth_Non_abated*0.35*School_Comm_Rate_A)+(F11*0.35*School_Comm_Rate_A),IF(AND(F7>0,F8>0),(F9*0.35*School_Comm_Rate_A)+(F10*Land_Growth_Non_abated*0.35*School_Comm_Rate_A)+(F11*Apartments_Non_abated*0.35*School_Comm_Rate_A),0)))) -> 20274.104 | G16: =IF(AND(G7=0,G8=0),(G9*0.35*School_Comm_Rate_A)+(G10*0.35*School_Comm_Rate_A)+(G11*0.35*School_Comm_Rate_A),IF(AND(G7=0,G8>0),(G9*0.35*School_Comm_Rate_A)+(G10*0.35*School_Comm_Rate_A)+(G11*Apartments_Non_abated*0.35*School_Comm_Rate_A),IF(AND(G7>0,G8=0),(G9*0.35*School_Comm_Rate_A)+(G10*Land_Growth_Non_abated*0.35*School_Comm_Rate_A)+(G11*0.35*School_Comm_Rate_A),IF(AND(G7>0,G8>0),(G9*0.35*School_Comm_Rate_A)+(G10*Land_Growth_Non_abated*0.35*School_Comm_Rate_A)+(G11*Apartments_Non_abated*0.35*School_Comm_Rate_A),0)))) -> 20274.104 | H16: =IF(AND(H7=0,H8=0),(H9*0.35*School_Comm_Rate_A)+(H10*0.35*School_Comm_Rate_A)+(H11*0.35*School_Comm_Rate_A),IF(AND(H7=0,H8>0),(H9*0.35*School_Comm_Rate_A)+(H10*0.35*School_Comm_Rate_A)+(H11*Apartments_Non_abated*0.35*School_Comm_Rate_A),IF(AND(H7>0,H8=0),(H9*0.35*School_Comm_Rate_A)+(H10*Land_Growth_Non_abated*0.35*School_Comm_Rate_A)+(H11*0.35*School_Comm_Rate_A),IF(AND(H7>0,H8>0),(H9*0.35*School_Comm_Rate_A)+(H10*Land_Growth_Non_abated*0.35*School_Comm_Rate_A)+(H11*Apartments_Non_abated*0.35*School_Comm_Rate_A),0)))) -> 20274.104 | I16: =IF(AND(I7=0,I8=0),(I9*0.35*School_Comm_Rate_A)+(I10*0.35*School_Comm_Rate_A)+(I11*0.35*School_Comm_Rate_A),IF(AND(I7=0,I8>0),(I9*0.35*School_Comm_Rate_A)+(I10*0.35*School_Comm_Rate_A)+(I11*Apartments_Non_abated*0.35*School_Comm_Rate_A),IF(AND(I7>0,I8=0),(I9*0.35*School_Comm_Rate_A)+(I10*Land_Growth_Non_abated*0.35*School_Comm_Rate_A)+(I11*0.35*School_Comm_Rate_A),IF(AND(I7>0,I8>0),(I9*0.35*School_Comm_Rate_A)+(I10*Land_Growth_Non_abated*0.35*School_Comm_Rate_A)+(I11*Apartments_Non_abated*0.35*School_Comm_Rate_A),0)))) -> 20274.104 | ... AE16: =IF(AND(AE7=0,AE8=0),(AE9*0.35*School_Comm_Rate_A)+(AE10*0.35*School_Comm_Rate_A)+(AE11*0.35*School_Comm_Rate_A),IF(AND(AE7=0,AE8>0),(AE9*0.35*School_Comm_Rate_A)+(AE10*0.35*School_Comm_Rate_A)+(AE11*Apartments_Non_abated*0.35*School_Comm_Rate_A),IF(AND(AE7>0,AE8=0),(AE9*0.35*School_Comm_Rate_A)+(AE10*Land_Growth_Non_abated*0.35*School_Comm_Rate_A)+(AE11*0.35*School_Comm_Rate_A),IF(AND(AE7>0,AE8>0),(AE9*0.35*School_Comm_Rate_A)+(AE10*Land_Growth_Non_abated*0.35*School_Comm_Rate_A)+(AE11*Apartments_Non_abated*0.35*School_Comm_Rate_A),0)))) -> 1388139.8
A17: Tax to non school | B17: =(B9*0.35*Non_School_Comm_Rate_A) -> 7211.7151 | C17: =(C9*0.35*Non_School_Comm_Rate_A) -> 7211.7151 | D17: =(D9*0.35*Non_School_Comm_Rate_A) -> 7211.7151 | E17: =(E9*0.35*Non_School_Comm_Rate_A) -> 7211.7151 | F17: =(F9*0.35*Non_School_Comm_Rate_A) -> 7211.7151 | G17: =(G9*0.35*Non_School_Comm_Rate_A) -> 7211.7151 | H17: =(H9*0.35*Non_School_Comm_Rate_A) -> 7211.7151 | I17: =(I9*0.35*Non_School_Comm_Rate_A) -> 7211.7151 | ... AE17: =(AE9*0.35*Non_School_Comm_Rate_A) -> 7211.7151
A18: TIF collection | B18: =IF(AND(B7=0,B8=0),(B10*0.35*Non_School_Comm_Rate_A)+(B11*0.35*Non_School_Comm_Rate_A),IF(AND(B7=0,B8>0),(B10*0.35*Non_School_Comm_Rate_A)+(B11*Apartments_Non_abated*0.35*Non_School_Comm_Rate_A),IF(AND(B7>0,B8=0),(B10*Land_Growth_Non_abated*0.35*Non_School_Comm_Rate_A)+(B11*Apartments_Non_abated*0.35*Non_School_Comm_Rate_A),IF(AND(B7>0,B8>0),(B10*Land_Growth_Non_abated*0.35*Non_School_Comm_Rate_A)+(B11*Apartments_Non_abated*0.35*Non_School_Comm_Rate_A),0)))) -> 0 | C18: =IF(AND(C7=0,C8=0),(C10*0.35*Non_School_Comm_Rate_A)+(C11*0.35*Non_School_Comm_Rate_A),IF(AND(C7=0,C8>0),(C10*0.35*Non_School_Comm_Rate_A)+(C11*Apartments_Non_abated*0.35*Non_School_Comm_Rate_A),IF(AND(C7>0,C8=0),(C10*Land_Growth_Non_abated*0.35*Non_School_Comm_Rate_A)+(C11*Apartments_Non_abated*0.35*Non_School_Comm_Rate_A),IF(AND(C7>0,C8>0),(C10*Land_Growth_Non_abated*0.35*Non_School_Comm_Rate_A)+(C11*Apartments_Non_abated*0.35*Non_School_Comm_Rate_A),0)))) -> 0 | D18: =IF(AND(D7=0,D8=0),(D10*0.35*Non_School_Comm_Rate_A)+(D11*0.35*Non_School_Comm_Rate_A),IF(AND(D7=0,D8>0),(D10*0.35*Non_School_Comm_Rate_A)+(D11*Apartments_Non_abated*0.35*Non_School_Comm_Rate_A),IF(AND(D7>0,D8=0),(D10*Land_Growth_Non_abated*0.35*Non_School_Comm_Rate_A)+(D11*Apartments_Non_abated*0.35*Non_School_Comm_Rate_A),IF(AND(D7>0,D8>0),(D10*Land_Growth_Non_abated*0.35*Non_School_Comm_Rate_A)+(D11*Apartments_Non_abated*0.35*Non_School_Comm_Rate_A),0)))) -> 0 | E18: =IF(AND(E7=0,E8=0),(E10*0.35*Non_School_Comm_Rate_A)+(E11*0.35*Non_School_Comm_Rate_A),IF(AND(E7=0,E8>0),(E10*0.35*Non_School_Comm_Rate_A)+(E11*Apartments_Non_abated*0.35*Non_School_Comm_Rate_A),IF(AND(E7>0,E8=0),(E10*Land_Growth_Non_abated*0.35*Non_School_Comm_Rate_A)+(E11*Apartments_Non_abated*0.35*Non_School_Comm_Rate_A),IF(AND(E7>0,E8>0),(E10*Land_Growth_Non_abated*0.35*Non_School_Comm_Rate_A)+(E11*Apartments_Non_abated*0.35*Non_School_Comm_Rate_A),0)))) -> 0 | F18: =IF(AND(F7=0,F8=0),(F10*0.35*Non_School_Comm_Rate_A)+(F11*0.35*Non_School_Comm_Rate_A),IF(AND(F7=0,F8>0),(F10*0.35*Non_School_Comm_Rate_A)+(F11*Apartments_Non_abated*0.35*Non_School_Comm_Rate_A),IF(AND(F7>0,F8=0),(F10*Land_Growth_Non_abated*0.35*Non_School_Comm_Rate_A)+(F11*Apartments_Non_abated*0.35*Non_School_Comm_Rate_A),IF(AND(F7>0,F8>0),(F10*Land_Growth_Non_abated*0.35*Non_School_Comm_Rate_A)+(F11*Apartments_Non_abated*0.35*Non_School_Comm_Rate_A),0)))) -> 0 | G18: =IF(AND(G7=0,G8=0),(G10*0.35*Non_School_Comm_Rate_A)+(G11*0.35*Non_School_Comm_Rate_A),IF(AND(G7=0,G8>0),(G10*0.35*Non_School_Comm_Rate_A)+(G11*Apartments_Non_abated*0.35*Non_School_Comm_Rate_A),IF(AND(G7>0,G8=0),(G10*Land_Growth_Non_abated*0.35*Non_School_Comm_Rate_A)+(G11*Apartments_Non_abated*0.35*Non_School_Comm_Rate_A),IF(AND(G7>0,G8>0),(G10*Land_Growth_Non_abated*0.35*Non_School_Comm_Rate_A)+(G11*Apartments_Non_abated*0.35*Non_School_Comm_Rate_A),0)))) -> 0 | H18: =IF(AND(H7=0,H8=0),(H10*0.35*Non_School_Comm_Rate_A)+(H11*0.35*Non_School_Comm_Rate_A),IF(AND(H7=0,H8>0),(H10*0.35*Non_School_Comm_Rate_A)+(H11*Apartments_Non_abated*0.35*Non_School_Comm_Rate_A),IF(AND(H7>0,H8=0),(H10*Land_Growth_Non_abated*0.35*Non_School_Comm_Rate_A)+(H11*Apartments_Non_abated*0.35*Non_School_Comm_Rate_A),IF(AND(H7>0,H8>0),(H10*Land_Growth_Non_abated*0.35*Non_School_Comm_Rate_A)+(H11*Apartments_Non_abated*0.35*Non_School_Comm_Rate_A),0)))) -> 0 | I18: =IF(AND(I7=0,I8=0),(I10*0.35*Non_School_Comm_Rate_A)+(I11*0.35*Non_School_Comm_Rate_A),IF(AND(I7=0,I8>0),(I10*0.35*Non_School_Comm_Rate_A)+(I11*Apartments_Non_abated*0.35*Non_School_Comm_Rate_A),IF(AND(I7>0,I8=0),(I10*Land_Growth_Non_abated*0.35*Non_School_Comm_Rate_A)+(I11*Apartments_Non_abated*0.35*Non_School_Comm_Rate_A),IF(AND(I7>0,I8>0),(I10*Land_Growth_Non_abated*0.35*Non_School_Comm_Rate_A)+(I11*Apartments_Non_abated*0.35*Non_School_Comm_Rate_A),0)))) -> 0 | ... AE18: =IF(AND(AE7=0,AE8=0),(AE10*0.35*Non_School_Comm_Rate_A)+(AE11*0.35*Non_School_Comm_Rate_A),IF(AND(AE7=0,AE8>0),(AE10*0.35*Non_School_Comm_Rate_A)+(AE11*Apartments_Non_abated*0.35*Non_School_Comm_Rate_A),IF(AND(AE7>0,AE8=0),(AE10*Land_Growth_Non_abated*0.35*Non_School_Comm_Rate_A)+(AE11*Apartments_Non_abated*0.35*Non_School_Comm_Rate_A),IF(AND(AE7>0,AE8>0),(AE10*Land_Growth_Non_abated*0.35*Non_School_Comm_Rate_A)+(AE11*Apartments_Non_abated*0.35*Non_School_Comm_Rate_A),0)))) -> 486564.39
A19: CDC - land | B19: =IF(B7>0,B10*0.35*Land_Growth_CDC*Full_Comm_Rate_A,0) -> 0 | C19: =IF(C7>0,C10*0.35*Land_Growth_CDC*Full_Comm_Rate_A,0) -> 0 | D19: =IF(D7>0,D10*0.35*Land_Growth_CDC*Full_Comm_Rate_A,0) -> 73872.616 | E19: =IF(E7>0,E10*0.35*Land_Growth_CDC*Full_Comm_Rate_A,0) -> 78304.973 | F19: =IF(F7>0,F10*0.35*Land_Growth_CDC*Full_Comm_Rate_A,0) -> 78304.973 | G19: =IF(G7>0,G10*0.35*Land_Growth_CDC*Full_Comm_Rate_A,0) -> 78304.973 | H19: =IF(H7>0,H10*0.35*Land_Growth_CDC*Full_Comm_Rate_A,0) -> 80654.122 | I19: =IF(I7>0,I10*0.35*Land_Growth_CDC*Full_Comm_Rate_A,0) -> 80654.122 | ... AE19: =IF(AE7>0,AE10*0.35*Land_Growth_CDC*Full_Comm_Rate_A,0) -> 0
A20: CDC - Improvement | B20: =IF(B8>0,B11*0.35*Apartments_CDC*Full_Comm_Rate_A,0) -> 0 | C20: =IF(C8>0,C11*0.35*Apartments_CDC*Full_Comm_Rate_A,0) -> 0 | D20: =IF(D8>0,D11*0.35*Apartments_CDC*Full_Comm_Rate_A,0) -> 541732.52 | E20: =IF(E8>0,E11*0.35*Apartments_CDC*Full_Comm_Rate_A,0) -> 574236.47 | F20: =IF(F8>0,F11*0.35*Apartments_CDC*Full_Comm_Rate_A,0) -> 574236.47 | G20: =IF(G8>0,G11*0.35*Apartments_CDC*Full_Comm_Rate_A,0) -> 574236.47 | H20: =IF(H8>0,H11*0.35*Apartments_CDC*Full_Comm_Rate_A,0) -> 591463.56 | I20: =IF(I8>0,I11*0.35*Apartments_CDC*Full_Comm_Rate_A,0) -> 591463.56 | ... AE20: =IF(AE8>0,AE11*0.35*Apartments_CDC*Full_Comm_Rate_A,0) -> 0
A21: Construction service payments | B21: =IF(SUM(B18:B20)=0,IF(C21=0,IF(SUM(B18:B20)=0,SUM(C18:C20)*0.5,SUM(D18:D20)*0.25),SUM(D18:D20)*0.25),0) -> 153901.28 | C21: =IF(SUM(C18:C20)=0,IF(D21=0,IF(SUM(C18:C20)=0,SUM(D18:D20)*0.5,SUM(E18:E20)*0.25),SUM(E18:E20)*0.25),0) -> 307802.57 | D21: =IF(SUM(D18:D20)=0,IF(E21=0,IF(SUM(D18:D20)=0,SUM(E18:E20)*0.5,SUM(F18:F20)*0.25),SUM(F18:F20)*0.25),0) -> 0 | E21: =IF(SUM(E18:E20)=0,IF(F21=0,IF(SUM(E18:E20)=0,SUM(F18:F20)*0.5,SUM(G18:G20)*0.25),SUM(G18:G20)*0.25),0) -> 0 | F21: =IF(SUM(F18:F20)=0,IF(G21=0,IF(SUM(F18:F20)=0,SUM(G18:G20)*0.5,SUM(H18:H20)*0.25),SUM(H18:H20)*0.25),0) -> 0 | G21: =IF(SUM(G18:G20)=0,IF(H21=0,IF(SUM(G18:G20)=0,SUM(H18:H20)*0.5,SUM(I18:I20)*0.25),SUM(I18:I20)*0.25),0) -> 0 | H21: =IF(SUM(H18:H20)=0,IF(I21=0,IF(SUM(H18:H20)=0,SUM(I18:I20)*0.5,SUM(J18:J20)*0.25),SUM(J18:J20)*0.25),0) -> 0 | I21: =IF(SUM(I18:I20)=0,IF(J21=0,IF(SUM(I18:I20)=0,SUM(J18:J20)*0.5,SUM(K18:K20)*0.25),SUM(K18:K20)*0.25),0) -> 0 | ... AE21: =IF(SUM(AE18:AE20)=0,IF(AF21=0,IF(SUM(AE18:AE20)=0,SUM(AF18:AF20)*0.5,SUM(AG18:AG20)*0.25),SUM(AG18:AG20)*0.25),0) -> 0
A22: Abate. value retained | B22: =IF(B7=0,IF(B8=0,0,(B11*Apartments_Retained*0.35*Full_Comm_Rate_A)),((B10*Land_Growth_Retained*0.35*Full_Comm_Rate_A)+IF(B8=0,0,(B11*Apartments_Retained*0.35*Full_Comm_Rate_A)))) -> 0 | C22: =IF(C7=0,IF(C8=0,0,(C11*Apartments_Retained*0.35*Full_Comm_Rate_A)),((C10*Land_Growth_Retained*0.35*Full_Comm_Rate_A)+IF(C8=0,0,(C11*Apartments_Retained*0.35*Full_Comm_Rate_A)))) -> 0 | D22: =IF(D7=0,IF(D8=0,0,(D11*Apartments_Retained*0.35*Full_Comm_Rate_A)),((D10*Land_Growth_Retained*0.35*Full_Comm_Rate_A)+IF(D8=0,0,(D11*Apartments_Retained*0.35*Full_Comm_Rate_A)))) -> 615605.14 | E22: =IF(E7=0,IF(E8=0,0,(E11*Apartments_Retained*0.35*Full_Comm_Rate_A)),((E10*Land_Growth_Retained*0.35*Full_Comm_Rate_A)+IF(E8=0,0,(E11*Apartments_Retained*0.35*Full_Comm_Rate_A)))) -> 652541.44 | F22: =IF(F7=0,IF(F8=0,0,(F11*Apartments_Retained*0.35*Full_Comm_Rate_A)),((F10*Land_Growth_Retained*0.35*Full_Comm_Rate_A)+IF(F8=0,0,(F11*Apartments_Retained*0.35*Full_Comm_Rate_A)))) -> 652541.44 | G22: =IF(G7=0,IF(G8=0,0,(G11*Apartments_Retained*0.35*Full_Comm_Rate_A)),((G10*Land_Growth_Retained*0.35*Full_Comm_Rate_A)+IF(G8=0,0,(G11*Apartments_Retained*0.35*Full_Comm_Rate_A)))) -> 652541.44 | H22: =IF(H7=0,IF(H8=0,0,(H11*Apartments_Retained*0.35*Full_Comm_Rate_A)),((H10*Land_Growth_Retained*0.35*Full_Comm_Rate_A)+IF(H8=0,0,(H11*Apartments_Retained*0.35*Full_Comm_Rate_A)))) -> 672117.69 | I22: =IF(I7=0,IF(I8=0,0,(I11*Apartments_Retained*0.35*Full_Comm_Rate_A)),((I10*Land_Growth_Retained*0.35*Full_Comm_Rate_A)+IF(I8=0,0,(I11*Apartments_Retained*0.35*Full_Comm_Rate_A)))) -> 672117.69 | ... AE22: =IF(AE7=0,IF(AE8=0,0,(AE11*Apartments_Retained*0.35*Full_Comm_Rate_A)),((AE10*Land_Growth_Retained*0.35*Full_Comm_Rate_A)+IF(AE8=0,0,(AE11*Apartments_Retained*0.35*Full_Comm_Rate_A)))) -> 0
A23: Total Annual Collections | B23: =SUM(B16:B21) -> 181387.1 | C23: =SUM(C16:C21) -> 335288.39 | D23: =SUM(D16:D21) -> 643090.95 | E23: =SUM(E16:E21) -> 680027.26 | F23: =SUM(F16:F21) -> 680027.26 | G23: =SUM(G16:G21) -> 680027.26 | H23: =SUM(H16:H21) -> 699603.51 | I23: =SUM(I16:I21) -> 699603.51 | ... AE23: =SUM(AE16:AE21) -> 1881915.9
A24: TOTAL MINIMUM SERVICE PAYMENTS | B24: =IF(B25=0,SUM(B18:B21),"ERROR") -> 153901.28 | C24: =IF(C25=0,SUM(C18:C21),"ERROR") -> 307802.57 | D24: =IF(D25=0,SUM(D18:D21),"ERROR") -> 615605.14 | E24: =IF(E25=0,SUM(E18:E21),"ERROR") -> 652541.44 | F24: =IF(F25=0,SUM(F18:F21),"ERROR") -> 652541.44 | G24: =IF(G25=0,SUM(G18:G21),"ERROR") -> 652541.44 | H24: =IF(H25=0,SUM(H18:H21),"ERROR") -> 672117.69 | I24: =IF(I25=0,SUM(I18:I21),"ERROR") -> 672117.69 | ... AE24: =IF(AE25=0,SUM(AE18:AE21),"ERROR") -> 486564.39
A25: TAX VALUE TEST (SHOULD EQUAL ZERO) | B25: =SUM(B16:B20,B22)-B14 -> 0 | C25: =SUM(C16:C20,C22)-C14 -> 0 | D25: =SUM(D16:D20,D22)-D14 -> 0 | E25: =SUM(E16:E20,E22)-E14 -> 0 | F25: =SUM(F16:F20,F22)-F14 -> 0 | G25: =SUM(G16:G20,G22)-G14 -> 0 | H25: =SUM(H16:H20,H22)-H14 -> 0 | I25: =SUM(I16:I20,I22)-I14 -> 0 | ... AE25: =SUM(AE16:AE20,AE22)-AE14 -> 0
A27: =Assumptions!$A$13 -> Office
A28: Land abatement year | B28: =IF(Land_Growth_Term>0,1) -> 1 | C28: =IF(Land_Growth_Term>0,B28+1) -> 2 | D28: =IF(Land_Growth_Term>0,C28+1) -> 3 | E28: =IF(Land_Growth_Term>0,D28+1) -> 4 | F28: =IF(Land_Growth_Term>0,E28+1) -> 5 | G28: =IF(Land_Growth_Term>0,F28+1) -> 6 | H28: =IF(Land_Growth_Term>0,G28+1) -> 7 | I28: =IF(Land_Growth_Term>0,H28+1) -> 8 | J28: =IF(Land_Growth_Term>0,I28+1) -> 9 | K28: =IF(Land_Growth_Term>0,J28+1) -> 10
A29: Building abatement year | B29: =IF(Assumptions!$B$14>=B$2,0,IF(Assumptions!$B$14+1=B$2,1,IF(Assumptions!$B$14+15>=B$2,A29+1,0))) -> 0 | C29: =IF(Assumptions!$B$14>=C$2,0,IF(Assumptions!$B$14+1=C$2,1,IF(Assumptions!$B$14+15>=C$2,B29+1,0))) -> 0 | D29: =IF(Assumptions!$B$14>=D$2,0,IF(Assumptions!$B$14+1=D$2,1,IF(Assumptions!$B$14+15>=D$2,C29+1,0))) -> 1 | E29: =IF(Assumptions!$B$14>=E$2,0,IF(Assumptions!$B$14+1=E$2,1,IF(Assumptions!$B$14+15>=E$2,D29+1,0))) -> 2 | F29: =IF(Assumptions!$B$14>=F$2,0,IF(Assumptions!$B$14+1=F$2,1,IF(Assumptions!$B$14+15>=F$2,E29+1,0))) -> 3 | G29: =IF(Assumptions!$B$14>=G$2,0,IF(Assumptions!$B$14+1=G$2,1,IF(Assumptions!$B$14+15>=G$2,F29+1,0))) -> 4 | H29: =IF(Assumptions!$B$14>=H$2,0,IF(Assumptions!$B$14+1=H$2,1,IF(Assumptions!$B$14+15>=H$2,G29+1,0))) -> 5 | I29: =IF(Assumptions!$B$14>=I$2,0,IF(Assumptions!$B$14+1=I$2,1,IF(Assumptions!$B$14+15>=I$2,H29+1,0))) -> 6 | ... AE29: =IF(Assumptions!$B$14>=AE$2,0,IF(Assumptions!$B$14+1=AE$2,1,IF(Assumptions!$B$14+15>=AE$2,AD29+1,0))) -> 0
A30: Base value | B30: =Office_Base_Val -> 139862.5 | C30: =B30 -> 139862.5 | D30: =C30 -> 139862.5 | E30: =D30 -> 139862.5 | F30: =E30 -> 139862.5 | G30: =F30 -> 139862.5 | H30: =G30 -> 139862.5 | I30: =H30 -> 139862.5 | J30: =I30 -> 139862.5 | ... AE30: =AD30 -> 139862.5
A31: Land growth | B31: =IF(B$2<=Assumptions!$B$14,0,IF(B$2=Assumptions!$B$14+1,Office_Land_Growth*(1+B$4),IF(B$2>Assumptions!$B$14,A31*(1+B$3),0))) -> 0 | C31: =IF(C$2<=Assumptions!$B$14,0,IF(C$2=Assumptions!$B$14+1,Office_Land_Growth*(1+C$4),IF(C$2>Assumptions!$B$14,B31*(1+C$3),0))) -> 0 | D31: =IF(D$2<=Assumptions!$B$14,0,IF(D$2=Assumptions!$B$14+1,Office_Land_Growth*(1+D$4),IF(D$2>Assumptions!$B$14,C31*(1+D$3),0))) -> 833080.99 | E31: =IF(E$2<=Assumptions!$B$14,0,IF(E$2=Assumptions!$B$14+1,Office_Land_Growth*(1+E$4),IF(E$2>Assumptions!$B$14,D31*(1+E$3),0))) -> 883065.85 | F31: =IF(F$2<=Assumptions!$B$14,0,IF(F$2=Assumptions!$B$14+1,Office_Land_Growth*(1+F$4),IF(F$2>Assumptions!$B$14,E31*(1+F$3),0))) -> 883065.85 | G31: =IF(G$2<=Assumptions!$B$14,0,IF(G$2=Assumptions!$B$14+1,Office_Land_Growth*(1+G$4),IF(G$2>Assumptions!$B$14,F31*(1+G$3),0))) -> 883065.85 | H31: =IF(H$2<=Assumptions!$B$14,0,IF(H$2=Assumptions!$B$14+1,Office_Land_Growth*(1+H$4),IF(H$2>Assumptions!$B$14,G31*(1+H$3),0))) -> 909557.83 | I31: =IF(I$2<=Assumptions!$B$14,0,IF(I$2=Assumptions!$B$14+1,Office_Land_Growth*(1+I$4),IF(I$2>Assumptions!$B$14,H31*(1+I$3),0))) -> 909557.83 | ... AE31: =IF(AE$2<=Assumptions!$B$14,0,IF(AE$2=Assumptions!$B$14+1,Office_Land_Growth*(1+AE$4),IF(AE$2>Assumptions!$B$14,AD31*(1+AE$3),0))) -> 1254773.8
A32: Improvement value | B32: =IF(B$2<=Assumptions!$B$14,0,IF(B$2=Assumptions!$B$14+1,Office_Impvt_Val*(1+B$4),IF(B$2>Assumptions!$B$14,A32*(1+B$3),0))) -> 0 | C32: =IF(C$2<=Assumptions!$B$14,0,IF(C$2=Assumptions!$B$14+1,Office_Impvt_Val*(1+C$4),IF(C$2>Assumptions!$B$14,B32*(1+C$3),0))) -> 0 | D32: =IF(D$2<=Assumptions!$B$14,0,IF(D$2=Assumptions!$B$14+1,Office_Impvt_Val*(1+D$4),IF(D$2>Assumptions!$B$14,C32*(1+D$3),0))) -> 6109260.6 | E32: =IF(E$2<=Assumptions!$B$14,0,IF(E$2=Assumptions!$B$14+1,Office_Impvt_Val*(1+E$4),IF(E$2>Assumptions!$B$14,D32*(1+E$3),0))) -> 6475816.3 | F32: =IF(F$2<=Assumptions!$B$14,0,IF(F$2=Assumptions!$B$14+1,Office_Impvt_Val*(1+F$4),IF(F$2>Assumptions!$B$14,E32*(1+F$3),0))) -> 6475816.3 | G32: =IF(G$2<=Assumptions!$B$14,0,IF(G$2=Assumptions!$B$14+1,Office_Impvt_Val*(1+G$4),IF(G$2>Assumptions!$B$14,F32*(1+G$3),0))) -> 6475816.3 | H32: =IF(H$2<=Assumptions!$B$14,0,IF(H$2=Assumptions!$B$14+1,Office_Impvt_Val*(1+H$4),IF(H$2>Assumptions!$B$14,G32*(1+H$3),0))) -> 6670090.8 | I32: =IF(I$2<=Assumptions!$B$14,0,IF(I$2=Assumptions!$B$14+1,Office_Impvt_Val*(1+I$4),IF(I$2>Assumptions!$B$14,H32*(1+I$3),0))) -> 6670090.8 | ... AE32: =IF(AE$2<=Assumptions!$B$14,0,IF(AE$2=Assumptions!$B$14+1,Office_Impvt_Val*(1+AE$4),IF(AE$2>Assumptions!$B$14,AD32*(1+AE$3),0))) -> 9201674.8
A33: Full Value Tax
A34: Full value | B34: =SUM(B30:B32) -> 139862.5 | C34: =SUM(C30:C32) -> 139862.5 | D34: =SUM(D30:D32) -> 7082204.1 | E34: =SUM(E30:E32) -> 7498744.6 | F34: =SUM(F30:F32) -> 7498744.6 | G34: =SUM(G30:G32) -> 7498744.6 | H34: =SUM(H30:H32) -> 7719511.1 | I34: =SUM(I30:I32) -> 7719511.1 | ... AE34: =SUM(AE30:AE32) -> 10596311
A35: Full tax | B35: =B34*0.35*Full_Comm_Rate_A -> 4422.0923 | C35: =C34*0.35*Full_Comm_Rate_A -> 4422.0923 | D35: =D34*0.35*Full_Comm_Rate_A -> 223921.07 | E35: =E34*0.35*Full_Comm_Rate_A -> 237091.01 | F35: =F34*0.35*Full_Comm_Rate_A -> 237091.01 | G35: =G34*0.35*Full_Comm_Rate_A -> 237091.01 | H35: =H34*0.35*Full_Comm_Rate_A -> 244071.08 | I35: =I34*0.35*Full_Comm_Rate_A -> 244071.08 | ... AE35: =AE34*0.35*Full_Comm_Rate_A -> 335028.09
A36: Collection Items
A37: Tax to school | B37: =IF(AND(B28=0,B29=0),(B30*0.35*School_Comm_Rate_A)+(B31*0.35*School_Comm_Rate_A)+(B32*0.35*School_Comm_Rate_A),IF(AND(B28=0,B29>0),(B30*0.35*School_Comm_Rate_A)+(B31*0.35*School_Comm_Rate_A)+(B32*Office_Non_abated*0.35*School_Comm_Rate_A),IF(AND(B28>0,B29=0),(B30*0.35*School_Comm_Rate_A)+(B31*Land_Growth_Non_abated*0.35*School_Comm_Rate_A)+(B32*0.35*School_Comm_Rate_A),IF(AND(B28>0,B29>0),(B30*0.35*School_Comm_Rate_A)+(B31*Land_Growth_Non_abated*0.35*School_Comm_Rate_A)+(B32*Office_Non_abated*0.35*School_Comm_Rate_A),0)))) -> 3261.826 | C37: =IF(AND(C28=0,C29=0),(C30*0.35*School_Comm_Rate_A)+(C31*0.35*School_Comm_Rate_A)+(C32*0.35*School_Comm_Rate_A),IF(AND(C28=0,C29>0),(C30*0.35*School_Comm_Rate_A)+(C31*0.35*School_Comm_Rate_A)+(C32*Office_Non_abated*0.35*School_Comm_Rate_A),IF(AND(C28>0,C29=0),(C30*0.35*School_Comm_Rate_A)+(C31*Land_Growth_Non_abated*0.35*School_Comm_Rate_A)+(C32*0.35*School_Comm_Rate_A),IF(AND(C28>0,C29>0),(C30*0.35*School_Comm_Rate_A)+(C31*Land_Growth_Non_abated*0.35*School_Comm_Rate_A)+(C32*Office_Non_abated*0.35*School_Comm_Rate_A),0)))) -> 3261.826 | D37: =IF(AND(D28=0,D29=0),(D30*0.35*School_Comm_Rate_A)+(D31*0.35*School_Comm_Rate_A)+(D32*0.35*School_Comm_Rate_A),IF(AND(D28=0,D29>0),(D30*0.35*School_Comm_Rate_A)+(D31*0.35*School_Comm_Rate_A)+(D32*Office_Non_abated*0.35*School_Comm_Rate_A),IF(AND(D28>0,D29=0),(D30*0.35*School_Comm_Rate_A)+(D31*Land_Growth_Non_abated*0.35*School_Comm_Rate_A)+(D32*0.35*School_Comm_Rate_A),IF(AND(D28>0,D29>0),(D30*0.35*School_Comm_Rate_A)+(D31*Land_Growth_Non_abated*0.35*School_Comm_Rate_A)+(D32*Office_Non_abated*0.35*School_Comm_Rate_A),0)))) -> 38881.355 | E37: =IF(AND(E28=0,E29=0),(E30*0.35*School_Comm_Rate_A)+(E31*0.35*School_Comm_Rate_A)+(E32*0.35*School_Comm_Rate_A),IF(AND(E28=0,E29>0),(E30*0.35*School_Comm_Rate_A)+(E31*0.35*School_Comm_Rate_A)+(E32*Office_Non_abated*0.35*School_Comm_Rate_A),IF(AND(E28>0,E29=0),(E30*0.35*School_Comm_Rate_A)+(E31*Land_Growth_Non_abated*0.35*School_Comm_Rate_A)+(E32*0.35*School_Comm_Rate_A),IF(AND(E28>0,E29>0),(E30*0.35*School_Comm_Rate_A)+(E31*Land_Growth_Non_abated*0.35*School_Comm_Rate_A)+(E32*Office_Non_abated*0.35*School_Comm_Rate_A),0)))) -> 41018.527 | F37: =IF(AND(F28=0,F29=0),(F30*0.35*School_Comm_Rate_A)+(F31*0.35*School_Comm_Rate_A)+(F32*0.35*School_Comm_Rate_A),IF(AND(F28=0,F29>0),(F30*0.35*School_Comm_Rate_A)+(F31*0.35*School_Comm_Rate_A)+(F32*Office_Non_abated*0.35*School_Comm_Rate_A),IF(AND(F28>0,F29=0),(F30*0.35*School_Comm_Rate_A)+(F31*Land_Growth_Non_abated*0.35*School_Comm_Rate_A)+(F32*0.35*School_Comm_Rate_A),IF(AND(F28>0,F29>0),(F30*0.35*School_Comm_Rate_A)+(F31*Land_Growth_Non_abated*0.35*School_Comm_Rate_A)+(F32*Office_Non_abated*0.35*School_Comm_Rate_A),0)))) -> 41018.527 | G37: =IF(AND(G28=0,G29=0),(G30*0.35*School_Comm_Rate_A)+(G31*0.35*School_Comm_Rate_A)+(G32*0.35*School_Comm_Rate_A),IF(AND(G28=0,G29>0),(G30*0.35*School_Comm_Rate_A)+(G31*0.35*School_Comm_Rate_A)+(G32*Office_Non_abated*0.35*School_Comm_Rate_A),IF(AND(G28>0,G29=0),(G30*0.35*School_Comm_Rate_A)+(G31*Land_Growth_Non_abated*0.35*School_Comm_Rate_A)+(G32*0.35*School_Comm_Rate_A),IF(AND(G28>0,G29>0),(G30*0.35*School_Comm_Rate_A)+(G31*Land_Growth_Non_abated*0.35*School_Comm_Rate_A)+(G32*Office_Non_abated*0.35*School_Comm_Rate_A),0)))) -> 41018.527 | H37: =IF(AND(H28=0,H29=0),(H30*0.35*School_Comm_Rate_A)+(H31*0.35*School_Comm_Rate_A)+(H32*0.35*School_Comm_Rate_A),IF(AND(H28=0,H29>0),(H30*0.35*School_Comm_Rate_A)+(H31*0.35*School_Comm_Rate_A)+(H32*Office_Non_abated*0.35*School_Comm_Rate_A),IF(AND(H28>0,H29=0),(H30*0.35*School_Comm_Rate_A)+(H31*Land_Growth_Non_abated*0.35*School_Comm_Rate_A)+(H32*0.35*School_Comm_Rate_A),IF(AND(H28>0,H29>0),(H30*0.35*School_Comm_Rate_A)+(H31*Land_Growth_Non_abated*0.35*School_Comm_Rate_A)+(H32*Office_Non_abated*0.35*School_Comm_Rate_A),0)))) -> 42151.228 | I37: =IF(AND(I28=0,I29=0),(I30*0.35*School_Comm_Rate_A)+(I31*0.35*School_Comm_Rate_A)+(I32*0.35*School_Comm_Rate_A),IF(AND(I28=0,I29>0),(I30*0.35*School_Comm_Rate_A)+(I31*0.35*School_Comm_Rate_A)+(I32*Office_Non_abated*0.35*School_Comm_Rate_A),IF(AND(I28>0,I29=0),(I30*0.35*School_Comm_Rate_A)+(I31*Land_Growth_Non_abated*0.35*School_Comm_Rate_A)+(I32*0.35*School_Comm_Rate_A),IF(AND(I28>0,I29>0),(I30*0.35*School_Comm_Rate_A)+(I31*Land_Growth_Non_abated*0.35*School_Comm_Rate_A)+(I32*Office_Non_abated*0.35*School_Comm_Rate_A),0)))) -> 42151.228 | ... AE37: =IF(AND(AE28=0,AE29=0),(AE30*0.35*School_Comm_Rate_A)+(AE31*0.35*School_Comm_Rate_A)+(AE32*0.35*School_Comm_Rate_A),IF(AND(AE28=0,AE29>0),(AE30*0.35*School_Comm_Rate_A)+(AE31*0.35*School_Comm_Rate_A)+(AE32*Office_Non_abated*0.35*School_Comm_Rate_A),IF(AND(AE28>0,AE29=0),(AE30*0.35*School_Comm_Rate_A)+(AE31*Land_Growth_Non_abated*0.35*School_Comm_Rate_A)+(AE32*0.35*School_Comm_Rate_A),IF(AND(AE28>0,AE29>0),(AE30*0.35*School_Comm_Rate_A)+(AE31*Land_Growth_Non_abated*0.35*School_Comm_Rate_A)+(AE32*Office_Non_abated*0.35*School_Comm_Rate_A),0)))) -> 247123.59
A38: Tax to non school | B38: =(B30*0.35*Non_School_Comm_Rate_A) -> 1160.2663 | C38: =(C30*0.35*Non_School_Comm_Rate_A) -> 1160.2663 | D38: =(D30*0.35*Non_School_Comm_Rate_A) -> 1160.2663 | E38: =(E30*0.35*Non_School_Comm_Rate_A) -> 1160.2663 | F38: =(F30*0.35*Non_School_Comm_Rate_A) -> 1160.2663 | G38: =(G30*0.35*Non_School_Comm_Rate_A) -> 1160.2663 | H38: =(H30*0.35*Non_School_Comm_Rate_A) -> 1160.2663 | I38: =(I30*0.35*Non_School_Comm_Rate_A) -> 1160.2663 | ... AE38: =(AE30*0.35*Non_School_Comm_Rate_A) -> 1160.2663
A39: TIF collection | B39: =IF(AND(B28=0,B29=0),(B31*0.35*Non_School_Comm_Rate_A)+(B32*0.35*Non_School_Comm_Rate_A),IF(AND(B28=0,B29>0),(B31*0.35*Non_School_Comm_Rate_A)+(B32*Office_Non_abated*0.35*Non_School_Comm_Rate_A),IF(AND(B28>0,B29=0),(B31*Land_Growth_Non_abated*0.35*Non_School_Comm_Rate_A)+(B32*Office_Non_abated*0.35*Non_School_Comm_Rate_A),IF(AND(B28>0,B29>0),(B31*Land_Growth_Non_abated*0.35*Non_School_Comm_Rate_A)+(B32*Office_Non_abated*0.35*Non_School_Comm_Rate_A),0)))) -> 0 | C39: =IF(AND(C28=0,C29=0),(C31*0.35*Non_School_Comm_Rate_A)+(C32*0.35*Non_School_Comm_Rate_A),IF(AND(C28=0,C29>0),(C31*0.35*Non_School_Comm_Rate_A)+(C32*Office_Non_abated*0.35*Non_School_Comm_Rate_A),IF(AND(C28>0,C29=0),(C31*Land_Growth_Non_abated*0.35*Non_School_Comm_Rate_A)+(C32*Office_Non_abated*0.35*Non_School_Comm_Rate_A),IF(AND(C28>0,C29>0),(C31*Land_Growth_Non_abated*0.35*Non_School_Comm_Rate_A)+(C32*Office_Non_abated*0.35*Non_School_Comm_Rate_A),0)))) -> 0 | D39: =IF(AND(D28=0,D29=0),(D31*0.35*Non_School_Comm_Rate_A)+(D32*0.35*Non_School_Comm_Rate_A),IF(AND(D28=0,D29>0),(D31*0.35*Non_School_Comm_Rate_A)+(D32*Office_Non_abated*0.35*Non_School_Comm_Rate_A),IF(AND(D28>0,D29=0),(D31*Land_Growth_Non_abated*0.35*Non_School_Comm_Rate_A)+(D32*Office_Non_abated*0.35*Non_School_Comm_Rate_A),IF(AND(D28>0,D29>0),(D31*Land_Growth_Non_abated*0.35*Non_School_Comm_Rate_A)+(D32*Office_Non_abated*0.35*Non_School_Comm_Rate_A),0)))) -> 12670.246 | E39: =IF(AND(E28=0,E29=0),(E31*0.35*Non_School_Comm_Rate_A)+(E32*0.35*Non_School_Comm_Rate_A),IF(AND(E28=0,E29>0),(E31*0.35*Non_School_Comm_Rate_A)+(E32*Office_Non_abated*0.35*Non_School_Comm_Rate_A),IF(AND(E28>0,E29=0),(E31*Land_Growth_Non_abated*0.35*Non_School_Comm_Rate_A)+(E32*Office_Non_abated*0.35*Non_School_Comm_Rate_A),IF(AND(E28>0,E29>0),(E31*Land_Growth_Non_abated*0.35*Non_School_Comm_Rate_A)+(E32*Office_Non_abated*0.35*Non_School_Comm_Rate_A),0)))) -> 13430.461 | F39: =IF(AND(F28=0,F29=0),(F31*0.35*Non_School_Comm_Rate_A)+(F32*0.35*Non_School_Comm_Rate_A),IF(AND(F28=0,F29>0),(F31*0.35*Non_School_Comm_Rate_A)+(F32*Office_Non_abated*0.35*Non_School_Comm_Rate_A),IF(AND(F28>0,F29=0),(F31*Land_Growth_Non_abated*0.35*Non_School_Comm_Rate_A)+(F32*Office_Non_abated*0.35*Non_School_Comm_Rate_A),IF(AND(F28>0,F29>0),(F31*Land_Growth_Non_abated*0.35*Non_School_Comm_Rate_A)+(F32*Office_Non_abated*0.35*Non_School_Comm_Rate_A),0)))) -> 13430.461 | G39: =IF(AND(G28=0,G29=0),(G31*0.35*Non_School_Comm_Rate_A)+(G32*0.35*Non_School_Comm_Rate_A),IF(AND(G28=0,G29>0),(G31*0.35*Non_School_Comm_Rate_A)+(G32*Office_Non_abated*0.35*Non_School_Comm_Rate_A),IF(AND(G28>0,G29=0),(G31*Land_Growth_Non_abated*0.35*Non_School_Comm_Rate_A)+(G32*Office_Non_abated*0.35*Non_School_Comm_Rate_A),IF(AND(G28>0,G29>0),(G31*Land_Growth_Non_abated*0.35*Non_School_Comm_Rate_A)+(G32*Office_Non_abated*0.35*Non_School_Comm_Rate_A),0)))) -> 13430.461 | H39: =IF(AND(H28=0,H29=0),(H31*0.35*Non_School_Comm_Rate_A)+(H32*0.35*Non_School_Comm_Rate_A),IF(AND(H28=0,H29>0),(H31*0.35*Non_School_Comm_Rate_A)+(H32*Office_Non_abated*0.35*Non_School_Comm_Rate_A),IF(AND(H28>0,H29=0),(H31*Land_Growth_Non_abated*0.35*Non_School_Comm_Rate_A)+(H32*Office_Non_abated*0.35*Non_School_Comm_Rate_A),IF(AND(H28>0,H29>0),(H31*Land_Growth_Non_abated*0.35*Non_School_Comm_Rate_A)+(H32*Office_Non_abated*0.35*Non_School_Comm_Rate_A),0)))) -> 13833.375 | I39: =IF(AND(I28=0,I29=0),(I31*0.35*Non_School_Comm_Rate_A)+(I32*0.35*Non_School_Comm_Rate_A),IF(AND(I28=0,I29>0),(I31*0.35*Non_School_Comm_Rate_A)+(I32*Office_Non_abated*0.35*Non_School_Comm_Rate_A),IF(AND(I28>0,I29=0),(I31*Land_Growth_Non_abated*0.35*Non_School_Comm_Rate_A)+(I32*Office_Non_abated*0.35*Non_School_Comm_Rate_A),IF(AND(I28>0,I29>0),(I31*Land_Growth_Non_abated*0.35*Non_School_Comm_Rate_A)+(I32*Office_Non_abated*0.35*Non_School_Comm_Rate_A),0)))) -> 13833.375 | ... AE39: =IF(AND(AE28=0,AE29=0),(AE31*0.35*Non_School_Comm_Rate_A)+(AE32*0.35*Non_School_Comm_Rate_A),IF(AND(AE28=0,AE29>0),(AE31*0.35*Non_School_Comm_Rate_A)+(AE32*Office_Non_abated*0.35*Non_School_Comm_Rate_A),IF(AND(AE28>0,AE29=0),(AE31*Land_Growth_Non_abated*0.35*Non_School_Comm_Rate_A)+(AE32*Office_Non_abated*0.35*Non_School_Comm_Rate_A),IF(AND(AE28>0,AE29>0),(AE31*Land_Growth_Non_abated*0.35*Non_School_Comm_Rate_A)+(AE32*Office_Non_abated*0.35*Non_School_Comm_Rate_A),0)))) -> 86744.23
A40: CDC - land | B40: =IF(B28>0,B31*0.35*Land_Growth_CDC*Full_Comm_Rate_A,0) -> 0 | C40: =IF(C28>0,C31*0.35*Land_Growth_CDC*Full_Comm_Rate_A,0) -> 0 | D40: =IF(D28>0,D31*0.35*Land_Growth_CDC*Full_Comm_Rate_A,0) -> 13169.939 | E40: =IF(E28>0,E31*0.35*Land_Growth_CDC*Full_Comm_Rate_A,0) -> 13960.135 | F40: =IF(F28>0,F31*0.35*Land_Growth_CDC*Full_Comm_Rate_A,0) -> 13960.135 | G40: =IF(G28>0,G31*0.35*Land_Growth_CDC*Full_Comm_Rate_A,0) -> 13960.135 | H40: =IF(H28>0,H31*0.35*Land_Growth_CDC*Full_Comm_Rate_A,0) -> 14378.939 | I40: =IF(I28>0,I31*0.35*Land_Growth_CDC*Full_Comm_Rate_A,0) -> 14378.939 | ... AE40: =IF(AE28>0,AE31*0.35*Land_Growth_CDC*Full_Comm_Rate_A,0) -> 0
A41: CDC - Improvement | B41: =IF(B29>0,B32*0.35*Office_CDC*Full_Comm_Rate_A,0) -> 0 | C41: =IF(C29>0,C32*0.35*Office_CDC*Full_Comm_Rate_A,0) -> 0 | D41: =IF(D29>0,D32*0.35*Office_CDC*Full_Comm_Rate_A,0) -> 48289.775 | E41: =IF(E29>0,E32*0.35*Office_CDC*Full_Comm_Rate_A,0) -> 51187.162 | F41: =IF(F29>0,F32*0.35*Office_CDC*Full_Comm_Rate_A,0) -> 51187.162 | G41: =IF(G29>0,G32*0.35*Office_CDC*Full_Comm_Rate_A,0) -> 51187.162 | H41: =IF(H29>0,H32*0.35*Office_CDC*Full_Comm_Rate_A,0) -> 52722.776 | I41: =IF(I29>0,I32*0.35*Office_CDC*Full_Comm_Rate_A,0) -> 52722.776 | ... AE41: =IF(AE29>0,AE32*0.35*Office_CDC*Full_Comm_Rate_A,0) -> 0
A42: Construction service payments | B42: =IF(SUM(B39:B41)=0,IF(C42=0,IF(SUM(B39:B41)=0,SUM(C39:C41)*0.5,SUM(D39:D41)*0.25),SUM(D39:D41)*0.25),0) -> 18532.49 | C42: =IF(SUM(C39:C41)=0,IF(D42=0,IF(SUM(C39:C41)=0,SUM(D39:D41)*0.5,SUM(E39:E41)*0.25),SUM(E39:E41)*0.25),0) -> 37064.98 | D42: =IF(SUM(D39:D41)=0,IF(E42=0,IF(SUM(D39:D41)=0,SUM(E39:E41)*0.5,SUM(F39:F41)*0.25),SUM(F39:F41)*0.25),0) -> 0 | E42: =IF(SUM(E39:E41)=0,IF(F42=0,IF(SUM(E39:E41)=0,SUM(F39:F41)*0.5,SUM(G39:G41)*0.25),SUM(G39:G41)*0.25),0) -> 0 | F42: =IF(SUM(F39:F41)=0,IF(G42=0,IF(SUM(F39:F41)=0,SUM(G39:G41)*0.5,SUM(H39:H41)*0.25),SUM(H39:H41)*0.25),0) -> 0 | G42: =IF(SUM(G39:G41)=0,IF(H42=0,IF(SUM(G39:G41)=0,SUM(H39:H41)*0.5,SUM(I39:I41)*0.25),SUM(I39:I41)*0.25),0) -> 0 | H42: =IF(SUM(H39:H41)=0,IF(I42=0,IF(SUM(H39:H41)=0,SUM(I39:I41)*0.5,SUM(J39:J41)*0.25),SUM(J39:J41)*0.25),0) -> 0 | I42: =IF(SUM(I39:I41)=0,IF(J42=0,IF(SUM(I39:I41)=0,SUM(J39:J41)*0.5,SUM(K39:K41)*0.25),SUM(K39:K41)*0.25),0) -> 0 | ... AE42: =IF(SUM(AE39:AE41)=0,IF(AF42=0,IF(SUM(AE39:AE41)=0,SUM(AF39:AF41)*0.5,SUM(AG39:AG41)*0.25),SUM(AG39:AG41)*0.25),0) -> 0
A43: Abate. value retained | B43: =IF(B28=0,IF(B29=0,0,(B32*Office_Retained*0.35*Full_Comm_Rate_A)),((B31*Land_Growth_Retained*0.35*Full_Comm_Rate_A)+IF(B29=0,0,(B32*Office_Retained*0.35*Full_Comm_Rate_A)))) -> 0 | C43: =IF(C28=0,IF(C29=0,0,(C32*Office_Retained*0.35*Full_Comm_Rate_A)),((C31*Land_Growth_Retained*0.35*Full_Comm_Rate_A)+IF(C29=0,0,(C32*Office_Retained*0.35*Full_Comm_Rate_A)))) -> 0 | D43: =IF(D28=0,IF(D29=0,0,(D32*Office_Retained*0.35*Full_Comm_Rate_A)),((D31*Land_Growth_Retained*0.35*Full_Comm_Rate_A)+IF(D29=0,0,(D32*Office_Retained*0.35*Full_Comm_Rate_A)))) -> 109749.49 | E43: =IF(E28=0,IF(E29=0,0,(E32*Office_Retained*0.35*Full_Comm_Rate_A)),((E31*Land_Growth_Retained*0.35*Full_Comm_Rate_A)+IF(E29=0,0,(E32*Office_Retained*0.35*Full_Comm_Rate_A)))) -> 116334.46 | F43: =IF(F28=0,IF(F29=0,0,(F32*Office_Retained*0.35*Full_Comm_Rate_A)),((F31*Land_Growth_Retained*0.35*Full_Comm_Rate_A)+IF(F29=0,0,(F32*Office_Retained*0.35*Full_Comm_Rate_A)))) -> 116334.46 | G43: =IF(G28=0,IF(G29=0,0,(G32*Office_Retained*0.35*Full_Comm_Rate_A)),((G31*Land_Growth_Retained*0.35*Full_Comm_Rate_A)+IF(G29=0,0,(G32*Office_Retained*0.35*Full_Comm_Rate_A)))) -> 116334.46 | H43: =IF(H28=0,IF(H29=0,0,(H32*Office_Retained*0.35*Full_Comm_Rate_A)),((H31*Land_Growth_Retained*0.35*Full_Comm_Rate_A)+IF(H29=0,0,(H32*Office_Retained*0.35*Full_Comm_Rate_A)))) -> 119824.49 | I43: =IF(I28=0,IF(I29=0,0,(I32*Office_Retained*0.35*Full_Comm_Rate_A)),((I31*Land_Growth_Retained*0.35*Full_Comm_Rate_A)+IF(I29=0,0,(I32*Office_Retained*0.35*Full_Comm_Rate_A)))) -> 119824.49 | ... AE43: =IF(AE28=0,IF(AE29=0,0,(AE32*Office_Retained*0.35*Full_Comm_Rate_A)),((AE31*Land_Growth_Retained*0.35*Full_Comm_Rate_A)+IF(AE29=0,0,(AE32*Office_Retained*0.35*Full_Comm_Rate_A)))) -> 0
A44: Total Annual Collections | B44: =SUM(B37:B42) -> 22954.582 | C44: =SUM(C37:C42) -> 41487.072 | D44: =SUM(D37:D42) -> 114171.58 | E44: =SUM(E37:E42) -> 120756.55 | F44: =SUM(F37:F42) -> 120756.55 | G44: =SUM(G37:G42) -> 120756.55 | H44: =SUM(H37:H42) -> 124246.58 | I44: =SUM(I37:I42) -> 124246.58 | ... AE44: =SUM(AE37:AE42) -> 335028.09
A45: TOTAL MINIMUM SERVICE PAYMENTS | B45: =IF(B46=0,SUM(B39:B42),"ERROR") -> 18532.49 | C45: =IF(C46=0,SUM(C39:C42),"ERROR") -> 37064.98 | D45: =IF(D46=0,SUM(D39:D42),"ERROR") -> 74129.96 | E45: =IF(E46=0,SUM(E39:E42),"ERROR") -> 78577.758 | F45: =IF(F46=0,SUM(F39:F42),"ERROR") -> 78577.758 | G45: =IF(G46=0,SUM(G39:G42),"ERROR") -> 78577.758 | H45: =IF(H46=0,SUM(H39:H42),"ERROR") -> 80935.09 | I45: =IF(I46=0,SUM(I39:I42),"ERROR") -> 80935.09 | ... AE45: =IF(AE46=0,SUM(AE39:AE42),"ERROR") -> 86744.23
A46: TAX VALUE TEST (SHOULD EQUAL ZERO) | B46: =SUM(B37:B41,B43)-B35 -> 0 | C46: =SUM(C37:C41,C43)-C35 -> 0 | D46: =SUM(D37:D41,D43)-D35 -> 0 | E46: =SUM(E37:E41,E43)-E35 -> 0 | F46: =SUM(F37:F41,F43)-F35 -> 0 | G46: =SUM(G37:G41,G43)-G35 -> 0 | H46: =SUM(H37:H41,H43)-H35 -> 0 | I46: =SUM(I37:I41,I43)-I35 -> 0 | ... AE46: =SUM(AE37:AE41,AE43)-AE35 -> 0
A48: =Assumptions!$C$2 -> Single-Family Homes
A49: Homes built | B49: =Assumptions!D5 -> 12 | C49: =B49 -> 12 | D49: =C49 -> 12 | E49: =D49 -> 12 | F49: =E49 -> 12 | G49: =F49 -> 12 | H49: =G49 -> 12 | I49: =H49 -> 12 | J49: =I49 -> 12 | ... AE49: =AD49 -> 12
A50: Land abatement year | B50: =IF(Land_Growth_Term>0,1) -> 1 | C50: =IF(Land_Growth_Term>0,B50+1) -> 2 | D50: =IF(Land_Growth_Term>0,C50+1) -> 3 | E50: =IF(Land_Growth_Term>0,D50+1) -> 4 | F50: =IF(Land_Growth_Term>0,E50+1) -> 5 | G50: =IF(Land_Growth_Term>0,F50+1) -> 6 | H50: =IF(Land_Growth_Term>0,G50+1) -> 7 | I50: =IF(Land_Growth_Term>0,H50+1) -> 8 | J50: =IF(Land_Growth_Term>0,I50+1) -> 9 | K50: =IF(Land_Growth_Term>0,J50+1) -> 10
A51: Building abatement year | B51: =IF(Assumptions!$D$3>=B$2,0,IF(Assumptions!$D$3+1=B$2,1,IF(Assumptions!$D$3+15>=B$2,A51+1,0))) -> 0 | C51: =IF(Assumptions!$D$3>=C$2,0,IF(Assumptions!$D$3+1=C$2,1,IF(Assumptions!$D$3+15>=C$2,B51+1,0))) -> 0 | D51: =IF(Assumptions!$D$3>=D$2,0,IF(Assumptions!$D$3+1=D$2,1,IF(Assumptions!$D$3+15>=D$2,C51+1,0))) -> 0 | E51: =IF(Assumptions!$D$3>=E$2,0,IF(Assumptions!$D$3+1=E$2,1,IF(Assumptions!$D$3+15>=E$2,D51+1,0))) -> 1 | F51: =IF(Assumptions!$D$3>=F$2,0,IF(Assumptions!$D$3+1=F$2,1,IF(Assumptions!$D$3+15>=F$2,E51+1,0))) -> 2 | G51: =IF(Assumptions!$D$3>=G$2,0,IF(Assumptions!$D$3+1=G$2,1,IF(Assumptions!$D$3+15>=G$2,F51+1,0))) -> 3 | H51: =IF(Assumptions!$D$3>=H$2,0,IF(Assumptions!$D$3+1=H$2,1,IF(Assumptions!$D$3+15>=H$2,G51+1,0))) -> 4 | I51: =IF(Assumptions!$D$3>=I$2,0,IF(Assumptions!$D$3+1=I$2,1,IF(Assumptions!$D$3+15>=I$2,H51+1,0))) -> 5 | ... AE51: =IF(Assumptions!$D$3>=AE$2,0,IF(Assumptions!$D$3+1=AE$2,1,IF(Assumptions!$D$3+15>=AE$2,AD51+1,0))) -> 0
A52: Base value | B52: =Residential_Base_Val -> 358450 | C52: =B52 -> 358450 | D52: =C52 -> 358450 | E52: =D52 -> 358450 | F52: =E52 -> 358450 | G52: =F52 -> 358450 | H52: =G52 -> 358450 | I52: =H52 -> 358450 | J52: =I52 -> 358450 | ... AE52: =AD52 -> 358450
A53: Land growth | B53: =IF(B$2<=Assumptions!$D$3,0,IF(B$2=Assumptions!$D$3+1,Residential_Land_Growth*(1+B$4),IF(B$2>Assumptions!$D$3,A53*(1+B$3),0))) -> 0 | C53: =IF(C$2<=Assumptions!$D$3,0,IF(C$2=Assumptions!$D$3+1,Residential_Land_Growth*(1+C$4),IF(C$2>Assumptions!$D$3,B53*(1+C$3),0))) -> 0 | D53: =IF(D$2<=Assumptions!$D$3,0,IF(D$2=Assumptions!$D$3+1,Residential_Land_Growth*(1+D$4),IF(D$2>Assumptions!$D$3,C53*(1+D$3),0))) -> 0 | E53: =IF(E$2<=Assumptions!$D$3,0,IF(E$2=Assumptions!$D$3+1,Residential_Land_Growth*(1+E$4),IF(E$2>Assumptions!$D$3,D53*(1+E$3),0))) -> 1132181.3 | F53: =IF(F$2<=Assumptions!$D$3,0,IF(F$2=Assumptions!$D$3+1,Residential_Land_Growth*(1+F$4),IF(F$2>Assumptions!$D$3,E53*(1+F$3),0))) -> 1132181.3 | G53: =IF(G$2<=Assumptions!$D$3,0,IF(G$2=Assumptions!$D$3+1,Residential_Land_Growth*(1+G$4),IF(G$2>Assumptions!$D$3,F53*(1+G$3),0))) -> 1132181.3 | H53: =IF(H$2<=Assumptions!$D$3,0,IF(H$2=Assumptions!$D$3+1,Residential_Land_Growth*(1+H$4),IF(H$2>Assumptions!$D$3,G53*(1+H$3),0))) -> 1166146.8 | I53: =IF(I$2<=Assumptions!$D$3,0,IF(I$2=Assumptions!$D$3+1,Residential_Land_Growth*(1+I$4),IF(I$2>Assumptions!$D$3,H53*(1+I$3),0))) -> 1166146.8 | ... AE53: =IF(AE$2<=Assumptions!$D$3,0,IF(AE$2=Assumptions!$D$3+1,Residential_Land_Growth*(1+AE$4),IF(AE$2>Assumptions!$D$3,AD53*(1+AE$3),0))) -> 1608749.2
A54: Improvement value | B54: =IF(B$2<=Assumptions!$D$3,0,IF(B$2=Assumptions!$D$3+1,Assumptions!$D$10*(1+B$4),IF(B$2>Assumptions!$D$3,A54*(1+B$3),0))) -> 0 | C54: =IF(C$2<=Assumptions!$D$3,0,IF(C$2=Assumptions!$D$3+1,Assumptions!$D$10*(1+C$4),IF(C$2>Assumptions!$D$3,B54*(1+C$3),0))) -> 0 | D54: =IF(D$2<=Assumptions!$D$3,0,IF(D$2=Assumptions!$D$3+1,Assumptions!$D$10*(1+D$4),IF(D$2>Assumptions!$D$3,C54*(1+D$3),0))) -> 0 | E54: =IF(E$2<=Assumptions!$D$3,0,IF(E$2=Assumptions!$D$3+1,Assumptions!$D$10*(1+E$4),IF(E$2>Assumptions!$D$3,D54*(1+E$3),0))) -> 8302663 | F54: =IF(F$2<=Assumptions!$D$3,0,IF(F$2=Assumptions!$D$3+1,Assumptions!$D$10*(1+F$4),IF(F$2>Assumptions!$D$3,E54*(1+F$3),0))) -> 8302663 | G54: =IF(G$2<=Assumptions!$D$3,0,IF(G$2=Assumptions!$D$3+1,Assumptions!$D$10*(1+G$4),IF(G$2>Assumptions!$D$3,F54*(1+G$3),0))) -> 8302663 | H54: =IF(H$2<=Assumptions!$D$3,0,IF(H$2=Assumptions!$D$3+1,Assumptions!$D$10*(1+H$4),IF(H$2>Assumptions!$D$3,G54*(1+H$3),0))) -> 8551742.9 | I54: =IF(I$2<=Assumptions!$D$3,0,IF(I$2=Assumptions!$D$3+1,Assumptions!$D$10*(1+I$4),IF(I$2>Assumptions!$D$3,H54*(1+I$3),0))) -> 8551742.9 | ... AE54: =IF(AE$2<=Assumptions!$D$3,0,IF(AE$2=Assumptions!$D$3+1,Assumptions!$D$10*(1+AE$4),IF(AE$2>Assumptions!$D$3,AD54*(1+AE$3),0))) -> 11797494
A55: Full Value Tax
A56: Full value | B56: =SUM(B52:B54) -> 358450 | C56: =SUM(C52:C54) -> 358450 | D56: =SUM(D52:D54) -> 358450 | E56: =SUM(E52:E54) -> 9793294.3 | F56: =SUM(F52:F54) -> 9793294.3 | G56: =SUM(G52:G54) -> 9793294.3 | H56: =SUM(H52:H54) -> 10076340 | I56: =SUM(I52:I54) -> 10076340 | ... AE56: =SUM(AE52:AE54) -> 13764693
A57: Full tax | B57: =B56*0.35*Full_Res_Rate_A -> 10098.459 | C57: =C56*0.35*Full_Res_Rate_A -> 10098.459 | D57: =D56*0.35*Full_Res_Rate_A -> 10098.459 | E57: =E56*0.35*Full_Res_Rate_A -> 275902.31 | F57: =F56*0.35*Full_Res_Rate_A -> 275902.31 | G57: =G56*0.35*Full_Res_Rate_A -> 275902.31 | H57: =H56*0.35*Full_Res_Rate_A -> 283876.42 | I57: =I56*0.35*Full_Res_Rate_A -> 283876.42 | ... AE57: =AE56*0.35*Full_Res_Rate_A -> 387786.84
A58: Collection Items
A59: Tax to school | B59: =IF(AND(B50=0,B51=0),(B52*0.35*School_Res_Rate_A)+(B53*0.35*School_Res_Rate_A)+(B54*0.35*School_Res_Rate_A),IF(AND(B50=0,B51>0),(B52*0.35*School_Res_Rate_A)+(B53*0.35*School_Res_Rate_A)+(B54*Residential_Non_abated*0.35*School_Res_Rate_A),IF(AND(B50>0,B51=0),(B52*0.35*School_Res_Rate_A)+(B53*Land_Growth_Non_abated*0.35*School_Res_Rate_A)+(B54*0.35*School_Res_Rate_A),IF(AND(B50>0,B51>0),(B52*0.35*School_Res_Rate_A)+(B53*Land_Growth_Non_abated*0.35*School_Res_Rate_A)+(B54*Residential_Non_abated*0.35*School_Res_Rate_A),0)))) -> 7248.023 | C59: =IF(AND(C50=0,C51=0),(C52*0.35*School_Res_Rate_A)+(C53*0.35*School_Res_Rate_A)+(C54*0.35*School_Res_Rate_A),IF(AND(C50=0,C51>0),(C52*0.35*School_Res_Rate_A)+(C53*0.35*School_Res_Rate_A)+(C54*Residential_Non_abated*0.35*School_Res_Rate_A),IF(AND(C50>0,C51=0),(C52*0.35*School_Res_Rate_A)+(C53*Land_Growth_Non_abated*0.35*School_Res_Rate_A)+(C54*0.35*School_Res_Rate_A),IF(AND(C50>0,C51>0),(C52*0.35*School_Res_Rate_A)+(C53*Land_Growth_Non_abated*0.35*School_Res_Rate_A)+(C54*Residential_Non_abated*0.35*School_Res_Rate_A),0)))) -> 7248.023 | D59: =IF(AND(D50=0,D51=0),(D52*0.35*School_Res_Rate_A)+(D53*0.35*School_Res_Rate_A)+(D54*0.35*School_Res_Rate_A),IF(AND(D50=0,D51>0),(D52*0.35*School_Res_Rate_A)+(D53*0.35*School_Res_Rate_A)+(D54*Residential_Non_abated*0.35*School_Res_Rate_A),IF(AND(D50>0,D51=0),(D52*0.35*School_Res_Rate_A)+(D53*Land_Growth_Non_abated*0.35*School_Res_Rate_A)+(D54*0.35*School_Res_Rate_A),IF(AND(D50>0,D51>0),(D52*0.35*School_Res_Rate_A)+(D53*Land_Growth_Non_abated*0.35*School_Res_Rate_A)+(D54*Residential_Non_abated*0.35*School_Res_Rate_A),0)))) -> 7248.023 | E59: =IF(AND(E50=0,E51=0),(E52*0.35*School_Res_Rate_A)+(E53*0.35*School_Res_Rate_A)+(E54*0.35*School_Res_Rate_A),IF(AND(E50=0,E51>0),(E52*0.35*School_Res_Rate_A)+(E53*0.35*School_Res_Rate_A)+(E54*Residential_Non_abated*0.35*School_Res_Rate_A),IF(AND(E50>0,E51=0),(E52*0.35*School_Res_Rate_A)+(E53*Land_Growth_Non_abated*0.35*School_Res_Rate_A)+(E54*0.35*School_Res_Rate_A),IF(AND(E50>0,E51>0),(E52*0.35*School_Res_Rate_A)+(E53*Land_Growth_Non_abated*0.35*School_Res_Rate_A)+(E54*Residential_Non_abated*0.35*School_Res_Rate_A),0)))) -> 7248.023 | F59: =IF(AND(F50=0,F51=0),(F52*0.35*School_Res_Rate_A)+(F53*0.35*School_Res_Rate_A)+(F54*0.35*School_Res_Rate_A),IF(AND(F50=0,F51>0),(F52*0.35*School_Res_Rate_A)+(F53*0.35*School_Res_Rate_A)+(F54*Residential_Non_abated*0.35*School_Res_Rate_A),IF(AND(F50>0,F51=0),(F52*0.35*School_Res_Rate_A)+(F53*Land_Growth_Non_abated*0.35*School_Res_Rate_A)+(F54*0.35*School_Res_Rate_A),IF(AND(F50>0,F51>0),(F52*0.35*School_Res_Rate_A)+(F53*Land_Growth_Non_abated*0.35*School_Res_Rate_A)+(F54*Residential_Non_abated*0.35*School_Res_Rate_A),0)))) -> 7248.023 | G59: =IF(AND(G50=0,G51=0),(G52*0.35*School_Res_Rate_A)+(G53*0.35*School_Res_Rate_A)+(G54*0.35*School_Res_Rate_A),IF(AND(G50=0,G51>0),(G52*0.35*School_Res_Rate_A)+(G53*0.35*School_Res_Rate_A)+(G54*Residential_Non_abated*0.35*School_Res_Rate_A),IF(AND(G50>0,G51=0),(G52*0.35*School_Res_Rate_A)+(G53*Land_Growth_Non_abated*0.35*School_Res_Rate_A)+(G54*0.35*School_Res_Rate_A),IF(AND(G50>0,G51>0),(G52*0.35*School_Res_Rate_A)+(G53*Land_Growth_Non_abated*0.35*School_Res_Rate_A)+(G54*Residential_Non_abated*0.35*School_Res_Rate_A),0)))) -> 7248.023 | H59: =IF(AND(H50=0,H51=0),(H52*0.35*School_Res_Rate_A)+(H53*0.35*School_Res_Rate_A)+(H54*0.35*School_Res_Rate_A),IF(AND(H50=0,H51>0),(H52*0.35*School_Res_Rate_A)+(H53*0.35*School_Res_Rate_A)+(H54*Residential_Non_abated*0.35*School_Res_Rate_A),IF(AND(H50>0,H51=0),(H52*0.35*School_Res_Rate_A)+(H53*Land_Growth_Non_abated*0.35*School_Res_Rate_A)+(H54*0.35*School_Res_Rate_A),IF(AND(H50>0,H51>0),(H52*0.35*School_Res_Rate_A)+(H53*Land_Growth_Non_abated*0.35*School_Res_Rate_A)+(H54*Residential_Non_abated*0.35*School_Res_Rate_A),0)))) -> 7248.023 | I59: =IF(AND(I50=0,I51=0),(I52*0.35*School_Res_Rate_A)+(I53*0.35*School_Res_Rate_A)+(I54*0.35*School_Res_Rate_A),IF(AND(I50=0,I51>0),(I52*0.35*School_Res_Rate_A)+(I53*0.35*School_Res_Rate_A)+(I54*Residential_Non_abated*0.35*School_Res_Rate_A),IF(AND(I50>0,I51=0),(I52*0.35*School_Res_Rate_A)+(I53*Land_Growth_Non_abated*0.35*School_Res_Rate_A)+(I54*0.35*School_Res_Rate_A),IF(AND(I50>0,I51>0),(I52*0.35*School_Res_Rate_A)+(I53*Land_Growth_Non_abated*0.35*School_Res_Rate_A)+(I54*Residential_Non_abated*0.35*School_Res_Rate_A),0)))) -> 7248.023 | ... AE59: =IF(AND(AE50=0,AE51=0),(AE52*0.35*School_Res_Rate_A)+(AE53*0.35*School_Res_Rate_A)+(AE54*0.35*School_Res_Rate_A),IF(AND(AE50=0,AE51>0),(AE52*0.35*School_Res_Rate_A)+(AE53*0.35*School_Res_Rate_A)+(AE54*Residential_Non_abated*0.35*School_Res_Rate_A),IF(AND(AE50>0,AE51=0),(AE52*0.35*School_Res_Rate_A)+(AE53*Land_Growth_Non_abated*0.35*School_Res_Rate_A)+(AE54*0.35*School_Res_Rate_A),IF(AND(AE50>0,AE51>0),(AE52*0.35*School_Res_Rate_A)+(AE53*Land_Growth_Non_abated*0.35*School_Res_Rate_A)+(AE54*Residential_Non_abated*0.35*School_Res_Rate_A),0)))) -> 278328.4
A60: Tax to non school | B60: =(B52*0.35*Non_School_Res_Rate_A) -> 2850.4361 | C60: =(C52*0.35*Non_School_Res_Rate_A) -> 2850.4361 | D60: =(D52*0.35*Non_School_Res_Rate_A) -> 2850.4361 | E60: =(E52*0.35*Non_School_Res_Rate_A) -> 2850.4361 | F60: =(F52*0.35*Non_School_Res_Rate_A) -> 2850.4361 | G60: =(G52*0.35*Non_School_Res_Rate_A) -> 2850.4361 | H60: =(H52*0.35*Non_School_Res_Rate_A) -> 2850.4361 | I60: =(I52*0.35*Non_School_Res_Rate_A) -> 2850.4361 | ... AE60: =(AE52*0.35*Non_School_Res_Rate_A) -> 2850.4361
A61: TIF collection | B61: =IF(AND(B50=0,B51=0),(B53*0.35*Non_School_Res_Rate_A)+(B54*0.35*Non_School_Res_Rate_A),IF(AND(B50=0,B51>0),(B53*0.35*Non_School_Res_Rate_A)+(B54*Residential_Non_abated*0.35*Non_School_Res_Rate_A),IF(AND(B50>0,B51=0),(B53*Land_Growth_Non_abated*0.35*Non_School_Res_Rate_A)+(B54*Residential_Non_abated*0.35*Non_School_Res_Rate_A),IF(AND(B50>0,B51>0),(B53*Land_Growth_Non_abated*0.35*Non_School_Res_Rate_A)+(B54*Residential_Non_abated*0.35*Non_School_Res_Rate_A),0)))) -> 0 | C61: =IF(AND(C50=0,C51=0),(C53*0.35*Non_School_Res_Rate_A)+(C54*0.35*Non_School_Res_Rate_A),IF(AND(C50=0,C51>0),(C53*0.35*Non_School_Res_Rate_A)+(C54*Residential_Non_abated*0.35*Non_School_Res_Rate_A),IF(AND(C50>0,C51=0),(C53*Land_Growth_Non_abated*0.35*Non_School_Res_Rate_A)+(C54*Residential_Non_abated*0.35*Non_School_Res_Rate_A),IF(AND(C50>0,C51>0),(C53*Land_Growth_Non_abated*0.35*Non_School_Res_Rate_A)+(C54*Residential_Non_abated*0.35*Non_School_Res_Rate_A),0)))) -> 0 | D61: =IF(AND(D50=0,D51=0),(D53*0.35*Non_School_Res_Rate_A)+(D54*0.35*Non_School_Res_Rate_A),IF(AND(D50=0,D51>0),(D53*0.35*Non_School_Res_Rate_A)+(D54*Residential_Non_abated*0.35*Non_School_Res_Rate_A),IF(AND(D50>0,D51=0),(D53*Land_Growth_Non_abated*0.35*Non_School_Res_Rate_A)+(D54*Residential_Non_abated*0.35*Non_School_Res_Rate_A),IF(AND(D50>0,D51>0),(D53*Land_Growth_Non_abated*0.35*Non_School_Res_Rate_A)+(D54*Residential_Non_abated*0.35*Non_School_Res_Rate_A),0)))) -> 0 | E61: =IF(AND(E50=0,E51=0),(E53*0.35*Non_School_Res_Rate_A)+(E54*0.35*Non_School_Res_Rate_A),IF(AND(E50=0,E51>0),(E53*0.35*Non_School_Res_Rate_A)+(E54*Residential_Non_abated*0.35*Non_School_Res_Rate_A),IF(AND(E50>0,E51=0),(E53*Land_Growth_Non_abated*0.35*Non_School_Res_Rate_A)+(E54*Residential_Non_abated*0.35*Non_School_Res_Rate_A),IF(AND(E50>0,E51>0),(E53*Land_Growth_Non_abated*0.35*Non_School_Res_Rate_A)+(E54*Residential_Non_abated*0.35*Non_School_Res_Rate_A),0)))) -> 0 | F61: =IF(AND(F50=0,F51=0),(F53*0.35*Non_School_Res_Rate_A)+(F54*0.35*Non_School_Res_Rate_A),IF(AND(F50=0,F51>0),(F53*0.35*Non_School_Res_Rate_A)+(F54*Residential_Non_abated*0.35*Non_School_Res_Rate_A),IF(AND(F50>0,F51=0),(F53*Land_Growth_Non_abated*0.35*Non_School_Res_Rate_A)+(F54*Residential_Non_abated*0.35*Non_School_Res_Rate_A),IF(AND(F50>0,F51>0),(F53*Land_Growth_Non_abated*0.35*Non_School_Res_Rate_A)+(F54*Residential_Non_abated*0.35*Non_School_Res_Rate_A),0)))) -> 0 | G61: =IF(AND(G50=0,G51=0),(G53*0.35*Non_School_Res_Rate_A)+(G54*0.35*Non_School_Res_Rate_A),IF(AND(G50=0,G51>0),(G53*0.35*Non_School_Res_Rate_A)+(G54*Residential_Non_abated*0.35*Non_School_Res_Rate_A),IF(AND(G50>0,G51=0),(G53*Land_Growth_Non_abated*0.35*Non_School_Res_Rate_A)+(G54*Residential_Non_abated*0.35*Non_School_Res_Rate_A),IF(AND(G50>0,G51>0),(G53*Land_Growth_Non_abated*0.35*Non_School_Res_Rate_A)+(G54*Residential_Non_abated*0.35*Non_School_Res_Rate_A),0)))) -> 0 | H61: =IF(AND(H50=0,H51=0),(H53*0.35*Non_School_Res_Rate_A)+(H54*0.35*Non_School_Res_Rate_A),IF(AND(H50=0,H51>0),(H53*0.35*Non_School_Res_Rate_A)+(H54*Residential_Non_abated*0.35*Non_School_Res_Rate_A),IF(AND(H50>0,H51=0),(H53*Land_Growth_Non_abated*0.35*Non_School_Res_Rate_A)+(H54*Residential_Non_abated*0.35*Non_School_Res_Rate_A),IF(AND(H50>0,H51>0),(H53*Land_Growth_Non_abated*0.35*Non_School_Res_Rate_A)+(H54*Residential_Non_abated*0.35*Non_School_Res_Rate_A),0)))) -> 0 | I61: =IF(AND(I50=0,I51=0),(I53*0.35*Non_School_Res_Rate_A)+(I54*0.35*Non_School_Res_Rate_A),IF(AND(I50=0,I51>0),(I53*0.35*Non_School_Res_Rate_A)+(I54*Residential_Non_abated*0.35*Non_School_Res_Rate_A),IF(AND(I50>0,I51=0),(I53*Land_Growth_Non_abated*0.35*Non_School_Res_Rate_A)+(I54*Residential_Non_abated*0.35*Non_School_Res_Rate_A),IF(AND(I50>0,I51>0),(I53*Land_Growth_Non_abated*0.35*Non_School_Res_Rate_A)+(I54*Residential_Non_abated*0.35*Non_School_Res_Rate_A),0)))) -> 0 | ... AE61: =IF(AND(AE50=0,AE51=0),(AE53*0.35*Non_School_Res_Rate_A)+(AE54*0.35*Non_School_Res_Rate_A),IF(AND(AE50=0,AE51>0),(AE53*0.35*Non_School_Res_Rate_A)+(AE54*Residential_Non_abated*0.35*Non_School_Res_Rate_A),IF(AND(AE50>0,AE51=0),(AE53*Land_Growth_Non_abated*0.35*Non_School_Res_Rate_A)+(AE54*Residential_Non_abated*0.35*Non_School_Res_Rate_A),IF(AND(AE50>0,AE51>0),(AE53*Land_Growth_Non_abated*0.35*Non_School_Res_Rate_A)+(AE54*Residential_Non_abated*0.35*Non_School_Res_Rate_A),0)))) -> 106608
A62: CDC - land | B62: =IF(B50>0,B53*0.35*Land_Growth_CDC*Full_Res_Rate_A,0) -> 0 | C62: =IF(C50>0,C53*0.35*Land_Growth_CDC*Full_Res_Rate_A,0) -> 0 | D62: =IF(D50>0,D53*0.35*Land_Growth_CDC*Full_Res_Rate_A,0) -> 0 | E62: =IF(E50>0,E53*0.35*Land_Growth_CDC*Full_Res_Rate_A,0) -> 15948.231 | F62: =IF(F50>0,F53*0.35*Land_Growth_CDC*Full_Res_Rate_A,0) -> 15948.231 | G62: =IF(G50>0,G53*0.35*Land_Growth_CDC*Full_Res_Rate_A,0) -> 15948.231 | H62: =IF(H50>0,H53*0.35*Land_Growth_CDC*Full_Res_Rate_A,0) -> 16426.678 | I62: =IF(I50>0,I53*0.35*Land_Growth_CDC*Full_Res_Rate_A,0) -> 16426.678 | ... AE62: =IF(AE50>0,AE53*0.35*Land_Growth_CDC*Full_Res_Rate_A,0) -> 0
A63: CDC - Improvement | B63: =IF(B51>0,B54*0.35*Residential_CDC*Full_Res_Rate_A,0) -> 0 | C63: =IF(C51>0,C54*0.35*Residential_CDC*Full_Res_Rate_A,0) -> 0 | D63: =IF(D51>0,D54*0.35*Residential_CDC*Full_Res_Rate_A,0) -> 0 | E63: =IF(E51>0,E54*0.35*Residential_CDC*Full_Res_Rate_A,0) -> 116953.69 | F63: =IF(F51>0,F54*0.35*Residential_CDC*Full_Res_Rate_A,0) -> 116953.69 | G63: =IF(G51>0,G54*0.35*Residential_CDC*Full_Res_Rate_A,0) -> 116953.69 | H63: =IF(H51>0,H54*0.35*Residential_CDC*Full_Res_Rate_A,0) -> 120462.3 | I63: =IF(I51>0,I54*0.35*Residential_CDC*Full_Res_Rate_A,0) -> 120462.3 | ... AE63: =IF(AE51>0,AE54*0.35*Residential_CDC*Full_Res_Rate_A,0) -> 0
A64: Construction service payments
A65: Abate. value retained | B65: =IF(B50=0,IF(B51=0,0,(B54*Residential_Retained*0.35*Full_Res_Rate_A)),((B53*Land_Growth_Retained*0.35*Full_Res_Rate_A)+IF(B51=0,0,(B54*Residential_Retained*0.35*Full_Res_Rate_A)))) -> 0 | C65: =IF(C50=0,IF(C51=0,0,(C54*Residential_Retained*0.35*Full_Res_Rate_A)),((C53*Land_Growth_Retained*0.35*Full_Res_Rate_A)+IF(C51=0,0,(C54*Residential_Retained*0.35*Full_Res_Rate_A)))) -> 0 | D65: =IF(D50=0,IF(D51=0,0,(D54*Residential_Retained*0.35*Full_Res_Rate_A)),((D53*Land_Growth_Retained*0.35*Full_Res_Rate_A)+IF(D51=0,0,(D54*Residential_Retained*0.35*Full_Res_Rate_A)))) -> 0 | E65: =IF(E50=0,IF(E51=0,0,(E54*Residential_Retained*0.35*Full_Res_Rate_A)),((E53*Land_Growth_Retained*0.35*Full_Res_Rate_A)+IF(E51=0,0,(E54*Residential_Retained*0.35*Full_Res_Rate_A)))) -> 132901.92 | F65: =IF(F50=0,IF(F51=0,0,(F54*Residential_Retained*0.35*Full_Res_Rate_A)),((F53*Land_Growth_Retained*0.35*Full_Res_Rate_A)+IF(F51=0,0,(F54*Residential_Retained*0.35*Full_Res_Rate_A)))) -> 132901.92 | G65: =IF(G50=0,IF(G51=0,0,(G54*Residential_Retained*0.35*Full_Res_Rate_A)),((G53*Land_Growth_Retained*0.35*Full_Res_Rate_A)+IF(G51=0,0,(G54*Residential_Retained*0.35*Full_Res_Rate_A)))) -> 132901.92 | H65: =IF(H50=0,IF(H51=0,0,(H54*Residential_Retained*0.35*Full_Res_Rate_A)),((H53*Land_Growth_Retained*0.35*Full_Res_Rate_A)+IF(H51=0,0,(H54*Residential_Retained*0.35*Full_Res_Rate_A)))) -> 136888.98 | I65: =IF(I50=0,IF(I51=0,0,(I54*Residential_Retained*0.35*Full_Res_Rate_A)),((I53*Land_Growth_Retained*0.35*Full_Res_Rate_A)+IF(I51=0,0,(I54*Residential_Retained*0.35*Full_Res_Rate_A)))) -> 136888.98 | ... AE65: =IF(AE50=0,IF(AE51=0,0,(AE54*Residential_Retained*0.35*Full_Res_Rate_A)),((AE53*Land_Growth_Retained*0.35*Full_Res_Rate_A)+IF(AE51=0,0,(AE54*Residential_Retained*0.35*Full_Res_Rate_A)))) -> 0
A66: Total Annual Collections | B66: =SUM(B59:B64) -> 10098.459 | C66: =SUM(C59:C64) -> 10098.459 | D66: =SUM(D59:D64) -> 10098.459 | E66: =SUM(E59:E64) -> 143000.38 | F66: =SUM(F59:F64) -> 143000.38 | G66: =SUM(G59:G64) -> 143000.38 | H66: =SUM(H59:H64) -> 146987.44 | I66: =SUM(I59:I64) -> 146987.44 | ... AE66: =SUM(AE59:AE64) -> 387786.84
A67: TOTAL MINIMUM SERVICE PAYMENTS | B67: =IF(B68=0,SUM(B61:B64),"ERROR") -> 0 | C67: =IF(C68=0,SUM(C61:C64),"ERROR") -> 0 | D67: =IF(D68=0,SUM(D61:D64),"ERROR") -> 0 | E67: =IF(E68=0,SUM(E61:E64),"ERROR") -> 132901.92 | F67: =IF(F68=0,SUM(F61:F64),"ERROR") -> 132901.92 | G67: =IF(G68=0,SUM(G61:G64),"ERROR") -> 132901.92 | H67: =IF(H68=0,SUM(H61:H64),"ERROR") -> 136888.98 | I67: =IF(I68=0,SUM(I61:I64),"ERROR") -> 136888.98 | ... AE67: =IF(AE68=0,SUM(AE61:AE64),"ERROR") -> 106608
A68: TAX VALUE TEST (SHOULD EQUAL ZERO) | B68: =SUM(B59:B63,B65)-B57 -> 0 | C68: =SUM(C59:C63,C65)-C57 -> 0 | D68: =SUM(D59:D63,D65)-D57 -> 0 | E68: =SUM(E59:E63,E65)-E57 -> 0 | F68: =SUM(F59:F63,F65)-F57 -> 0 | G68: =SUM(G59:G63,G65)-G57 -> 0 | H68: =SUM(H59:H63,H65)-H57 -> 0 | I68: =SUM(I59:I63,I65)-I57 -> 0 | ... AE68: =SUM(AE59:AE63,AE65)-AE57 -> 0
A70: =Assumptions!$C$13 -> Condos
A71: Homes built | C71: =Assumptions!D16 -> 31 | D71: =C71 -> 31 | E71: =D71 -> 31 | F71: =E71 -> 31 | G71: =F71 -> 31 | H71: =G71 -> 31 | I71: =H71 -> 31 | J71: =I71 -> 31 | K71: =J71 -> 31 | ... AE71: =AD71 -> 31
A72: Land abatement year | B72: =IF(Land_Growth_Term>0,1) -> 1 | C72: =IF(Land_Growth_Term>0,B72+1) -> 2 | D72: =IF(Land_Growth_Term>0,C72+1) -> 3 | E72: =IF(Land_Growth_Term>0,D72+1) -> 4 | F72: =IF(Land_Growth_Term>0,E72+1) -> 5 | G72: =IF(Land_Growth_Term>0,F72+1) -> 6 | H72: =IF(Land_Growth_Term>0,G72+1) -> 7 | I72: =IF(Land_Growth_Term>0,H72+1) -> 8 | J72: =IF(Land_Growth_Term>0,I72+1) -> 9 | K72: =IF(Land_Growth_Term>0,J72+1) -> 10
A73: Building abatement year | B73: =IF(Assumptions!$D$14>=B$2,0,IF(Assumptions!$D$14+1=B$2,1,IF(Assumptions!$D$14+15>=B$2,A73+1,0))) -> 0 | C73: =IF(Assumptions!$D$14>=C$2,0,IF(Assumptions!$D$14+1=C$2,1,IF(Assumptions!$D$14+15>=C$2,B73+1,0))) -> 0 | D73: =IF(Assumptions!$D$14>=D$2,0,IF(Assumptions!$D$14+1=D$2,1,IF(Assumptions!$D$14+15>=D$2,C73+1,0))) -> 0 | E73: =IF(Assumptions!$D$14>=E$2,0,IF(Assumptions!$D$14+1=E$2,1,IF(Assumptions!$D$14+15>=E$2,D73+1,0))) -> 1 | F73: =IF(Assumptions!$D$14>=F$2,0,IF(Assumptions!$D$14+1=F$2,1,IF(Assumptions!$D$14+15>=F$2,E73+1,0))) -> 2 | G73: =IF(Assumptions!$D$14>=G$2,0,IF(Assumptions!$D$14+1=G$2,1,IF(Assumptions!$D$14+15>=G$2,F73+1,0))) -> 3 | H73: =IF(Assumptions!$D$14>=H$2,0,IF(Assumptions!$D$14+1=H$2,1,IF(Assumptions!$D$14+15>=H$2,G73+1,0))) -> 4 | I73: =IF(Assumptions!$D$14>=I$2,0,IF(Assumptions!$D$14+1=I$2,1,IF(Assumptions!$D$14+15>=I$2,H73+1,0))) -> 5 | ... AE73: =IF(Assumptions!$D$14>=AE$2,0,IF(Assumptions!$D$14+1=AE$2,1,IF(Assumptions!$D$14+15>=AE$2,AD73+1,0))) -> 0
A74: Base value | B74: =Condos_Base_Val -> 88655.357 | C74: =B74 -> 88655.357 | D74: =C74 -> 88655.357 | E74: =D74 -> 88655.357 | F74: =E74 -> 88655.357 | G74: =F74 -> 88655.357 | H74: =G74 -> 88655.357 | I74: =H74 -> 88655.357 | J74: =I74 -> 88655.357 | ... AE74: =AD74 -> 88655.357
A75: Land growth | B75: =IF(B$2<=Assumptions!$D$14,0,IF(B$2=Assumptions!$D$14+1,Condos_Land_Growth*(1+B$4),IF(B$2>Assumptions!$D$14,A75*(1+B$3),0))) -> 0 | C75: =IF(C$2<=Assumptions!$D$14,0,IF(C$2=Assumptions!$D$14+1,Condos_Land_Growth*(1+C$4),IF(C$2>Assumptions!$D$14,B75*(1+C$3),0))) -> 0 | D75: =IF(D$2<=Assumptions!$D$14,0,IF(D$2=Assumptions!$D$14+1,Condos_Land_Growth*(1+D$4),IF(D$2>Assumptions!$D$14,C75*(1+D$3),0))) -> 0 | E75: =IF(E$2<=Assumptions!$D$14,0,IF(E$2=Assumptions!$D$14+1,Condos_Land_Growth*(1+E$4),IF(E$2>Assumptions!$D$14,D75*(1+E$3),0))) -> 2222207.5 | F75: =IF(F$2<=Assumptions!$D$14,0,IF(F$2=Assumptions!$D$14+1,Condos_Land_Growth*(1+F$4),IF(F$2>Assumptions!$D$14,E75*(1+F$3),0))) -> 2222207.5 | G75: =IF(G$2<=Assumptions!$D$14,0,IF(G$2=Assumptions!$D$14+1,Condos_Land_Growth*(1+G$4),IF(G$2>Assumptions!$D$14,F75*(1+G$3),0))) -> 2222207.5 | H75: =IF(H$2<=Assumptions!$D$14,0,IF(H$2=Assumptions!$D$14+1,Condos_Land_Growth*(1+H$4),IF(H$2>Assumptions!$D$14,G75*(1+H$3),0))) -> 2288873.8 | I75: =IF(I$2<=Assumptions!$D$14,0,IF(I$2=Assumptions!$D$14+1,Condos_Land_Growth*(1+I$4),IF(I$2>Assumptions!$D$14,H75*(1+I$3),0))) -> 2288873.8 | ... AE75: =IF(AE$2<=Assumptions!$D$14,0,IF(AE$2=Assumptions!$D$14+1,Condos_Land_Growth*(1+AE$4),IF(AE$2>Assumptions!$D$14,AD75*(1+AE$3),0))) -> 3157599
A76: Improvement value | B76: =IF(B$2<=Assumptions!$D$14,0,IF(B$2=Assumptions!$D$14+1,Condos_Impvt_Val*(1+B$4),IF(B$2>Assumptions!$D$14,A76*(1+B$3),0))) -> 0 | C76: =IF(C$2<=Assumptions!$D$14,0,IF(C$2=Assumptions!$D$14+1,Condos_Impvt_Val*(1+C$4),IF(C$2>Assumptions!$D$14,B76*(1+C$3),0))) -> 0 | D76: =IF(D$2<=Assumptions!$D$14,0,IF(D$2=Assumptions!$D$14+1,Condos_Impvt_Val*(1+D$4),IF(D$2>Assumptions!$D$14,C76*(1+D$3),0))) -> 0 | E76: =IF(E$2<=Assumptions!$D$14,0,IF(E$2=Assumptions!$D$14+1,Condos_Impvt_Val*(1+E$4),IF(E$2>Assumptions!$D$14,D76*(1+E$3),0))) -> 16296189 | F76: =IF(F$2<=Assumptions!$D$14,0,IF(F$2=Assumptions!$D$14+1,Condos_Impvt_Val*(1+F$4),IF(F$2>Assumptions!$D$14,E76*(1+F$3),0))) -> 16296189 | G76: =IF(G$2<=Assumptions!$D$14,0,IF(G$2=Assumptions!$D$14+1,Condos_Impvt_Val*(1+G$4),IF(G$2>Assumptions!$D$14,F76*(1+G$3),0))) -> 16296189 | H76: =IF(H$2<=Assumptions!$D$14,0,IF(H$2=Assumptions!$D$14+1,Condos_Impvt_Val*(1+H$4),IF(H$2>Assumptions!$D$14,G76*(1+H$3),0))) -> 16785074 | I76: =IF(I$2<=Assumptions!$D$14,0,IF(I$2=Assumptions!$D$14+1,Condos_Impvt_Val*(1+I$4),IF(I$2>Assumptions!$D$14,H76*(1+I$3),0))) -> 16785074 | ... AE76: =IF(AE$2<=Assumptions!$D$14,0,IF(AE$2=Assumptions!$D$14+1,Condos_Impvt_Val*(1+AE$4),IF(AE$2>Assumptions!$D$14,AD76*(1+AE$3),0))) -> 23155726
A77: Full Value Tax
A78: Full value | B78: =SUM(B74:B76) -> 88655.357 | C78: =SUM(C74:C76) -> 88655.357 | D78: =SUM(D74:D76) -> 88655.357 | E78: =SUM(E74:E76) -> 18607051 | F78: =SUM(F74:F76) -> 18607051 | G78: =SUM(G74:G76) -> 18607051 | H78: =SUM(H74:H76) -> 19162603 | I78: =SUM(I74:I76) -> 19162603 | ... AE78: =SUM(AE74:AE76) -> 26401980
A79: Full tax | B79: =B78*0.35*Full_Res_Rate_A -> 2497.6496 | C79: =C78*0.35*Full_Res_Rate_A -> 2497.6496 | D79: =D78*0.35*Full_Res_Rate_A -> 2497.6496 | E79: =E78*0.35*Full_Res_Rate_A -> 524208.53 | F79: =F78*0.35*Full_Res_Rate_A -> 524208.53 | G79: =G78*0.35*Full_Res_Rate_A -> 524208.53 | H79: =H78*0.35*Full_Res_Rate_A -> 539859.86 | I79: =I78*0.35*Full_Res_Rate_A -> 539859.86 | ... AE79: =AE78*0.35*Full_Res_Rate_A -> 743811.74
A80: Collection Items
A81: Tax to school | B81: =IF(AND(B72=0,B73=0),(B74*0.35*School_Res_Rate_A)+(B75*0.35*School_Res_Rate_A)+(B76*0.35*School_Res_Rate_A),IF(AND(B72=0,B73>0),(B74*0.35*School_Res_Rate_A)+(B75*0.35*School_Res_Rate_A)+(B76*Residential_Non_abated*0.35*School_Res_Rate_A),IF(AND(B72>0,B73=0),(B74*0.35*School_Res_Rate_A)+(B75*Land_Growth_Non_abated*0.35*School_Res_Rate_A)+(B76*0.35*School_Res_Rate_A),IF(AND(B72>0,B73>0),(B74*0.35*School_Res_Rate_A)+(B75*Land_Growth_Non_abated*0.35*School_Res_Rate_A)+(B76*Residential_Non_abated*0.35*School_Res_Rate_A),0)))) -> 1792.6519 | C81: =IF(AND(C72=0,C73=0),(C74*0.35*School_Res_Rate_A)+(C75*0.35*School_Res_Rate_A)+(C76*0.35*School_Res_Rate_A),IF(AND(C72=0,C73>0),(C74*0.35*School_Res_Rate_A)+(C75*0.35*School_Res_Rate_A)+(C76*Residential_Non_abated*0.35*School_Res_Rate_A),IF(AND(C72>0,C73=0),(C74*0.35*School_Res_Rate_A)+(C75*Land_Growth_Non_abated*0.35*School_Res_Rate_A)+(C76*0.35*School_Res_Rate_A),IF(AND(C72>0,C73>0),(C74*0.35*School_Res_Rate_A)+(C75*Land_Growth_Non_abated*0.35*School_Res_Rate_A)+(C76*Residential_Non_abated*0.35*School_Res_Rate_A),0)))) -> 1792.6519 | D81: =IF(AND(D72=0,D73=0),(D74*0.35*School_Res_Rate_A)+(D75*0.35*School_Res_Rate_A)+(D76*0.35*School_Res_Rate_A),IF(AND(D72=0,D73>0),(D74*0.35*School_Res_Rate_A)+(D75*0.35*School_Res_Rate_A)+(D76*Residential_Non_abated*0.35*School_Res_Rate_A),IF(AND(D72>0,D73=0),(D74*0.35*School_Res_Rate_A)+(D75*Land_Growth_Non_abated*0.35*School_Res_Rate_A)+(D76*0.35*School_Res_Rate_A),IF(AND(D72>0,D73>0),(D74*0.35*School_Res_Rate_A)+(D75*Land_Growth_Non_abated*0.35*School_Res_Rate_A)+(D76*Residential_Non_abated*0.35*School_Res_Rate_A),0)))) -> 1792.6519 | E81: =IF(AND(E72=0,E73=0),(E74*0.35*School_Res_Rate_A)+(E75*0.35*School_Res_Rate_A)+(E76*0.35*School_Res_Rate_A),IF(AND(E72=0,E73>0),(E74*0.35*School_Res_Rate_A)+(E75*0.35*School_Res_Rate_A)+(E76*Residential_Non_abated*0.35*School_Res_Rate_A),IF(AND(E72>0,E73=0),(E74*0.35*School_Res_Rate_A)+(E75*Land_Growth_Non_abated*0.35*School_Res_Rate_A)+(E76*0.35*School_Res_Rate_A),IF(AND(E72>0,E73>0),(E74*0.35*School_Res_Rate_A)+(E75*Land_Growth_Non_abated*0.35*School_Res_Rate_A)+(E76*Residential_Non_abated*0.35*School_Res_Rate_A),0)))) -> 1792.6519 | F81: =IF(AND(F72=0,F73=0),(F74*0.35*School_Res_Rate_A)+(F75*0.35*School_Res_Rate_A)+(F76*0.35*School_Res_Rate_A),IF(AND(F72=0,F73>0),(F74*0.35*School_Res_Rate_A)+(F75*0.35*School_Res_Rate_A)+(F76*Residential_Non_abated*0.35*School_Res_Rate_A),IF(AND(F72>0,F73=0),(F74*0.35*School_Res_Rate_A)+(F75*Land_Growth_Non_abated*0.35*School_Res_Rate_A)+(F76*0.35*School_Res_Rate_A),IF(AND(F72>0,F73>0),(F74*0.35*School_Res_Rate_A)+(F75*Land_Growth_Non_abated*0.35*School_Res_Rate_A)+(F76*Residential_Non_abated*0.35*School_Res_Rate_A),0)))) -> 1792.6519 | G81: =IF(AND(G72=0,G73=0),(G74*0.35*School_Res_Rate_A)+(G75*0.35*School_Res_Rate_A)+(G76*0.35*School_Res_Rate_A),IF(AND(G72=0,G73>0),(G74*0.35*School_Res_Rate_A)+(G75*0.35*School_Res_Rate_A)+(G76*Residential_Non_abated*0.35*School_Res_Rate_A),IF(AND(G72>0,G73=0),(G74*0.35*School_Res_Rate_A)+(G75*Land_Growth_Non_abated*0.35*School_Res_Rate_A)+(G76*0.35*School_Res_Rate_A),IF(AND(G72>0,G73>0),(G74*0.35*School_Res_Rate_A)+(G75*Land_Growth_Non_abated*0.35*School_Res_Rate_A)+(G76*Residential_Non_abated*0.35*School_Res_Rate_A),0)))) -> 1792.6519 | H81: =IF(AND(H72=0,H73=0),(H74*0.35*School_Res_Rate_A)+(H75*0.35*School_Res_Rate_A)+(H76*0.35*School_Res_Rate_A),IF(AND(H72=0,H73>0),(H74*0.35*School_Res_Rate_A)+(H75*0.35*School_Res_Rate_A)+(H76*Residential_Non_abated*0.35*School_Res_Rate_A),IF(AND(H72>0,H73=0),(H74*0.35*School_Res_Rate_A)+(H75*Land_Growth_Non_abated*0.35*School_Res_Rate_A)+(H76*0.35*School_Res_Rate_A),IF(AND(H72>0,H73>0),(H74*0.35*School_Res_Rate_A)+(H75*Land_Growth_Non_abated*0.35*School_Res_Rate_A)+(H76*Residential_Non_abated*0.35*School_Res_Rate_A),0)))) -> 1792.6519 | I81: =IF(AND(I72=0,I73=0),(I74*0.35*School_Res_Rate_A)+(I75*0.35*School_Res_Rate_A)+(I76*0.35*School_Res_Rate_A),IF(AND(I72=0,I73>0),(I74*0.35*School_Res_Rate_A)+(I75*0.35*School_Res_Rate_A)+(I76*Residential_Non_abated*0.35*School_Res_Rate_A),IF(AND(I72>0,I73=0),(I74*0.35*School_Res_Rate_A)+(I75*Land_Growth_Non_abated*0.35*School_Res_Rate_A)+(I76*0.35*School_Res_Rate_A),IF(AND(I72>0,I73>0),(I74*0.35*School_Res_Rate_A)+(I75*Land_Growth_Non_abated*0.35*School_Res_Rate_A)+(I76*Residential_Non_abated*0.35*School_Res_Rate_A),0)))) -> 1792.6519 | ... AE81: =IF(AND(AE72=0,AE73=0),(AE74*0.35*School_Res_Rate_A)+(AE75*0.35*School_Res_Rate_A)+(AE76*0.35*School_Res_Rate_A),IF(AND(AE72=0,AE73>0),(AE74*0.35*School_Res_Rate_A)+(AE75*0.35*School_Res_Rate_A)+(AE76*Residential_Non_abated*0.35*School_Res_Rate_A),IF(AND(AE72>0,AE73=0),(AE74*0.35*School_Res_Rate_A)+(AE75*Land_Growth_Non_abated*0.35*School_Res_Rate_A)+(AE76*0.35*School_Res_Rate_A),IF(AND(AE72>0,AE73>0),(AE74*0.35*School_Res_Rate_A)+(AE75*Land_Growth_Non_abated*0.35*School_Res_Rate_A)+(AE76*Residential_Non_abated*0.35*School_Res_Rate_A),0)))) -> 533860.12
A82: Tax to non school | B82: =(B74*0.35*Non_School_Res_Rate_A) -> 704.9977 | C82: =(C74*0.35*Non_School_Res_Rate_A) -> 704.9977 | D82: =(D74*0.35*Non_School_Res_Rate_A) -> 704.9977 | E82: =(E74*0.35*Non_School_Res_Rate_A) -> 704.9977 | F82: =(F74*0.35*Non_School_Res_Rate_A) -> 704.9977 | G82: =(G74*0.35*Non_School_Res_Rate_A) -> 704.9977 | H82: =(H74*0.35*Non_School_Res_Rate_A) -> 704.9977 | I82: =(I74*0.35*Non_School_Res_Rate_A) -> 704.9977 | ... AE82: =(AE74*0.35*Non_School_Res_Rate_A) -> 704.9977
A83: TIF collection | B83: =IF(AND(B72=0,B73=0),(B75*0.35*Non_School_Res_Rate_A)+(B76*0.35*Non_School_Res_Rate_A),IF(AND(B72=0,B73>0),(B75*0.35*Non_School_Res_Rate_A)+(B76*Residential_Non_abated*0.35*Non_School_Res_Rate_A),IF(AND(B72>0,B73=0),(B75*Land_Growth_Non_abated*0.35*Non_School_Res_Rate_A)+(B76*Residential_Non_abated*0.35*Non_School_Res_Rate_A),IF(AND(B72>0,B73>0),(B75*Land_Growth_Non_abated*0.35*Non_School_Res_Rate_A)+(B76*Residential_Non_abated*0.35*Non_School_Res_Rate_A),0)))) -> 0 | C83: =IF(AND(C72=0,C73=0),(C75*0.35*Non_School_Res_Rate_A)+(C76*0.35*Non_School_Res_Rate_A),IF(AND(C72=0,C73>0),(C75*0.35*Non_School_Res_Rate_A)+(C76*Residential_Non_abated*0.35*Non_School_Res_Rate_A),IF(AND(C72>0,C73=0),(C75*Land_Growth_Non_abated*0.35*Non_School_Res_Rate_A)+(C76*Residential_Non_abated*0.35*Non_School_Res_Rate_A),IF(AND(C72>0,C73>0),(C75*Land_Growth_Non_abated*0.35*Non_School_Res_Rate_A)+(C76*Residential_Non_abated*0.35*Non_School_Res_Rate_A),0)))) -> 0 | D83: =IF(AND(D72=0,D73=0),(D75*0.35*Non_School_Res_Rate_A)+(D76*0.35*Non_School_Res_Rate_A),IF(AND(D72=0,D73>0),(D75*0.35*Non_School_Res_Rate_A)+(D76*Residential_Non_abated*0.35*Non_School_Res_Rate_A),IF(AND(D72>0,D73=0),(D75*Land_Growth_Non_abated*0.35*Non_School_Res_Rate_A)+(D76*Residential_Non_abated*0.35*Non_School_Res_Rate_A),IF(AND(D72>0,D73>0),(D75*Land_Growth_Non_abated*0.35*Non_School_Res_Rate_A)+(D76*Residential_Non_abated*0.35*Non_School_Res_Rate_A),0)))) -> 0 | E83: =IF(AND(E72=0,E73=0),(E75*0.35*Non_School_Res_Rate_A)+(E76*0.35*Non_School_Res_Rate_A),IF(AND(E72=0,E73>0),(E75*0.35*Non_School_Res_Rate_A)+(E76*Residential_Non_abated*0.35*Non_School_Res_Rate_A),IF(AND(E72>0,E73=0),(E75*Land_Growth_Non_abated*0.35*Non_School_Res_Rate_A)+(E76*Residential_Non_abated*0.35*Non_School_Res_Rate_A),IF(AND(E72>0,E73>0),(E75*Land_Growth_Non_abated*0.35*Non_School_Res_Rate_A)+(E76*Residential_Non_abated*0.35*Non_School_Res_Rate_A),0)))) -> 0 | F83: =IF(AND(F72=0,F73=0),(F75*0.35*Non_School_Res_Rate_A)+(F76*0.35*Non_School_Res_Rate_A),IF(AND(F72=0,F73>0),(F75*0.35*Non_School_Res_Rate_A)+(F76*Residential_Non_abated*0.35*Non_School_Res_Rate_A),IF(AND(F72>0,F73=0),(F75*Land_Growth_Non_abated*0.35*Non_School_Res_Rate_A)+(F76*Residential_Non_abated*0.35*Non_School_Res_Rate_A),IF(AND(F72>0,F73>0),(F75*Land_Growth_Non_abated*0.35*Non_School_Res_Rate_A)+(F76*Residential_Non_abated*0.35*Non_School_Res_Rate_A),0)))) -> 0 | G83: =IF(AND(G72=0,G73=0),(G75*0.35*Non_School_Res_Rate_A)+(G76*0.35*Non_School_Res_Rate_A),IF(AND(G72=0,G73>0),(G75*0.35*Non_School_Res_Rate_A)+(G76*Residential_Non_abated*0.35*Non_School_Res_Rate_A),IF(AND(G72>0,G73=0),(G75*Land_Growth_Non_abated*0.35*Non_School_Res_Rate_A)+(G76*Residential_Non_abated*0.35*Non_School_Res_Rate_A),IF(AND(G72>0,G73>0),(G75*Land_Growth_Non_abated*0.35*Non_School_Res_Rate_A)+(G76*Residential_Non_abated*0.35*Non_School_Res_Rate_A),0)))) -> 0 | H83: =IF(AND(H72=0,H73=0),(H75*0.35*Non_School_Res_Rate_A)+(H76*0.35*Non_School_Res_Rate_A),IF(AND(H72=0,H73>0),(H75*0.35*Non_School_Res_Rate_A)+(H76*Residential_Non_abated*0.35*Non_School_Res_Rate_A),IF(AND(H72>0,H73=0),(H75*Land_Growth_Non_abated*0.35*Non_School_Res_Rate_A)+(H76*Residential_Non_abated*0.35*Non_School_Res_Rate_A),IF(AND(H72>0,H73>0),(H75*Land_Growth_Non_abated*0.35*Non_School_Res_Rate_A)+(H76*Residential_Non_abated*0.35*Non_School_Res_Rate_A),0)))) -> 0 | I83: =IF(AND(I72=0,I73=0),(I75*0.35*Non_School_Res_Rate_A)+(I76*0.35*Non_School_Res_Rate_A),IF(AND(I72=0,I73>0),(I75*0.35*Non_School_Res_Rate_A)+(I76*Residential_Non_abated*0.35*Non_School_Res_Rate_A),IF(AND(I72>0,I73=0),(I75*Land_Growth_Non_abated*0.35*Non_School_Res_Rate_A)+(I76*Residential_Non_abated*0.35*Non_School_Res_Rate_A),IF(AND(I72>0,I73>0),(I75*Land_Growth_Non_abated*0.35*Non_School_Res_Rate_A)+(I76*Residential_Non_abated*0.35*Non_School_Res_Rate_A),0)))) -> 0 | ... AE83: =IF(AND(AE72=0,AE73=0),(AE75*0.35*Non_School_Res_Rate_A)+(AE76*0.35*Non_School_Res_Rate_A),IF(AND(AE72=0,AE73>0),(AE75*0.35*Non_School_Res_Rate_A)+(AE76*Residential_Non_abated*0.35*Non_School_Res_Rate_A),IF(AND(AE72>0,AE73=0),(AE75*Land_Growth_Non_abated*0.35*Non_School_Res_Rate_A)+(AE76*Residential_Non_abated*0.35*Non_School_Res_Rate_A),IF(AND(AE72>0,AE73>0),(AE75*Land_Growth_Non_abated*0.35*Non_School_Res_Rate_A)+(AE76*Residential_Non_abated*0.35*Non_School_Res_Rate_A),0)))) -> 209246.62
A84: CDC - land | B84: =IF(B72>0,B75*0.35*Land_Growth_CDC*Full_Res_Rate_A,0) -> 0 | C84: =IF(C72>0,C75*0.35*Land_Growth_CDC*Full_Res_Rate_A,0) -> 0 | D84: =IF(D72>0,D75*0.35*Land_Growth_CDC*Full_Res_Rate_A,0) -> 0 | E84: =IF(E72>0,E75*0.35*Land_Growth_CDC*Full_Res_Rate_A,0) -> 31302.653 | F84: =IF(F72>0,F75*0.35*Land_Growth_CDC*Full_Res_Rate_A,0) -> 31302.653 | G84: =IF(G72>0,G75*0.35*Land_Growth_CDC*Full_Res_Rate_A,0) -> 31302.653 | H84: =IF(H72>0,H75*0.35*Land_Growth_CDC*Full_Res_Rate_A,0) -> 32241.732 | I84: =IF(I72>0,I75*0.35*Land_Growth_CDC*Full_Res_Rate_A,0) -> 32241.732 | ... AE84: =IF(AE72>0,AE75*0.35*Land_Growth_CDC*Full_Res_Rate_A,0) -> 0
A85: CDC - Improvement | B85: =IF(B73>0,B76*0.35*Residential_CDC*Full_Res_Rate_A,0) -> 0 | C85: =IF(C73>0,C76*0.35*Residential_CDC*Full_Res_Rate_A,0) -> 0 | D85: =IF(D73>0,D76*0.35*Residential_CDC*Full_Res_Rate_A,0) -> 0 | E85: =IF(E73>0,E76*0.35*Residential_CDC*Full_Res_Rate_A,0) -> 229552.79 | F85: =IF(F73>0,F76*0.35*Residential_CDC*Full_Res_Rate_A,0) -> 229552.79 | G85: =IF(G73>0,G76*0.35*Residential_CDC*Full_Res_Rate_A,0) -> 229552.79 | H85: =IF(H73>0,H76*0.35*Residential_CDC*Full_Res_Rate_A,0) -> 236439.37 | I85: =IF(I73>0,I76*0.35*Residential_CDC*Full_Res_Rate_A,0) -> 236439.37 | ... AE85: =IF(AE73>0,AE76*0.35*Residential_CDC*Full_Res_Rate_A,0) -> 0
A86: Construction service payments
A87: Abate. value retained | B87: =IF(B72=0,IF(B73=0,0,(B76*Residential_Retained*0.35*Full_Res_Rate_A)),((B75*Land_Growth_Retained*0.35*Full_Res_Rate_A)+IF(B73=0,0,(B76*Residential_Retained*0.35*Full_Res_Rate_A)))) -> 0 | C87: =IF(C72=0,IF(C73=0,0,(C76*Residential_Retained*0.35*Full_Res_Rate_A)),((C75*Land_Growth_Retained*0.35*Full_Res_Rate_A)+IF(C73=0,0,(C76*Residential_Retained*0.35*Full_Res_Rate_A)))) -> 0 | D87: =IF(D72=0,IF(D73=0,0,(D76*Residential_Retained*0.35*Full_Res_Rate_A)),((D75*Land_Growth_Retained*0.35*Full_Res_Rate_A)+IF(D73=0,0,(D76*Residential_Retained*0.35*Full_Res_Rate_A)))) -> 0 | E87: =IF(E72=0,IF(E73=0,0,(E76*Residential_Retained*0.35*Full_Res_Rate_A)),((E75*Land_Growth_Retained*0.35*Full_Res_Rate_A)+IF(E73=0,0,(E76*Residential_Retained*0.35*Full_Res_Rate_A)))) -> 260855.44 | F87: =IF(F72=0,IF(F73=0,0,(F76*Residential_Retained*0.35*Full_Res_Rate_A)),((F75*Land_Growth_Retained*0.35*Full_Res_Rate_A)+IF(F73=0,0,(F76*Residential_Retained*0.35*Full_Res_Rate_A)))) -> 260855.44 | G87: =IF(G72=0,IF(G73=0,0,(G76*Residential_Retained*0.35*Full_Res_Rate_A)),((G75*Land_Growth_Retained*0.35*Full_Res_Rate_A)+IF(G73=0,0,(G76*Residential_Retained*0.35*Full_Res_Rate_A)))) -> 260855.44 | H87: =IF(H72=0,IF(H73=0,0,(H76*Residential_Retained*0.35*Full_Res_Rate_A)),((H75*Land_Growth_Retained*0.35*Full_Res_Rate_A)+IF(H73=0,0,(H76*Residential_Retained*0.35*Full_Res_Rate_A)))) -> 268681.1 | I87: =IF(I72=0,IF(I73=0,0,(I76*Residential_Retained*0.35*Full_Res_Rate_A)),((I75*Land_Growth_Retained*0.35*Full_Res_Rate_A)+IF(I73=0,0,(I76*Residential_Retained*0.35*Full_Res_Rate_A)))) -> 268681.1 | ... AE87: =IF(AE72=0,IF(AE73=0,0,(AE76*Residential_Retained*0.35*Full_Res_Rate_A)),((AE75*Land_Growth_Retained*0.35*Full_Res_Rate_A)+IF(AE73=0,0,(AE76*Residential_Retained*0.35*Full_Res_Rate_A)))) -> 0
A88: Total Annual Collections | B88: =SUM(B81:B86) -> 2497.6496 | C88: =SUM(C81:C86) -> 2497.6496 | D88: =SUM(D81:D86) -> 2497.6496 | E88: =SUM(E81:E86) -> 263353.09 | F88: =SUM(F81:F86) -> 263353.09 | G88: =SUM(G81:G86) -> 263353.09 | H88: =SUM(H81:H86) -> 271178.75 | I88: =SUM(I81:I86) -> 271178.75 | ... AE88: =SUM(AE81:AE86) -> 743811.74
A89: TOTAL MINIMUM SERVICE PAYMENTS | B89: =IF(B90=0,SUM(B83:B86),"ERROR") -> 0 | C89: =IF(C90=0,SUM(C83:C86),"ERROR") -> 0 | D89: =IF(D90=0,SUM(D83:D86),"ERROR") -> 0 | E89: =IF(E90=0,SUM(E83:E86),"ERROR") -> 260855.44 | F89: =IF(F90=0,SUM(F83:F86),"ERROR") -> 260855.44 | G89: =IF(G90=0,SUM(G83:G86),"ERROR") -> 260855.44 | H89: =IF(H90=0,SUM(H83:H86),"ERROR") -> 268681.1 | I89: =IF(I90=0,SUM(I83:I86),"ERROR") -> 268681.1 | ... AE89: =IF(AE90=0,SUM(AE83:AE86),"ERROR") -> 209246.62
A90: TAX VALUE TEST (SHOULD EQUAL ZERO) | B90: =SUM(B81:B85,B87)-B79 -> 0 | C90: =SUM(C81:C85,C87)-C79 -> 0 | D90: =SUM(D81:D85,D87)-D79 -> 0 | E90: =SUM(E81:E85,E87)-E79 -> 0 | F90: =SUM(F81:F85,F87)-F79 -> 0 | G90: =SUM(G81:G85,G87)-G79 -> 0 | H90: =SUM(H81:H85,H87)-H79 -> 0 | I90: =SUM(I81:I85,I87)-I79 -> 0 | ... AE90: =SUM(AE81:AE85,AE87)-AE79 -> 0
A92: MINIMUM SERVICE PAYMENTS SUMMARY
A93: =A6 -> Apartments | B93: =Calculations!B24 -> 153901.28 | C93: =Calculations!C24 -> 307802.57 | D93: =Calculations!D24 -> 615605.14 | E93: =Calculations!E24 -> 652541.44 | F93: =Calculations!F24 -> 652541.44 | G93: =Calculations!G24 -> 652541.44 | H93: =Calculations!H24 -> 672117.69 | I93: =Calculations!I24 -> 672117.69 | ... AE93: =Calculations!AE24 -> 486564.39
A94: =A27 -> Office | B94: =Calculations!B45 -> 18532.49 | C94: =Calculations!C45 -> 37064.98 | D94: =Calculations!D45 -> 74129.96 | E94: =Calculations!E45 -> 78577.758 | F94: =Calculations!F45 -> 78577.758 | G94: =Calculations!G45 -> 78577.758 | H94: =Calculations!H45 -> 80935.09 | I94: =Calculations!I45 -> 80935.09 | ... AE94: =Calculations!AE45 -> 86744.23
A95: =A48 -> Single-Family Homes | B95: =B67 -> 0 | C95: =C67 -> 0 | D95: =D67 -> 0 | E95: =E67 -> 132901.92 | F95: =F67 -> 132901.92 | G95: =G67 -> 132901.92 | H95: =H67 -> 136888.98 | I95: =I67 -> 136888.98 | ... AE95: =AE67 -> 106608
A96: =A70 -> Condos | B96: =B89 -> 0 | C96: =C89 -> 0 | D96: =D89 -> 0 | E96: =E89 -> 260855.44 | F96: =F89 -> 260855.44 | G96: =G89 -> 260855.44 | H96: =H89 -> 268681.1 | I96: =I89 -> 268681.1 | ... AE96: =AE89 -> 209246.62
A97: TOTAL MINIMUM SERVICE PAYMENTS | B97: =SUM(B93:B96) -> 172433.77 | C97: =SUM(C93:C96) -> 344867.55 | D97: =SUM(D93:D96) -> 689735.1 | E97: =SUM(E93:E96) -> 1124876.6 | F97: =SUM(F93:F96) -> 1124876.6 | G97: =SUM(G93:G96) -> 1124876.6 | H97: =SUM(H93:H96) -> 1158622.9 | I97: =SUM(I93:I96) -> 1158622.9 | ... AE97: =SUM(AE93:AE96) -> 889163.25
A99: Debt Coverage
A100: Cash Flow | B100: =B97/Assumptions!$G$16 -> 156757.98 | C100: =C97/Assumptions!$G$16 -> 313515.95 | D100: =D97/Assumptions!$G$16 -> 627031.9 | E100: =E97/Assumptions!$G$16 -> 1022615.1 | F100: =F97/Assumptions!$G$16 -> 1022615.1 | G100: =G97/Assumptions!$G$16 -> 1022615.1 | H100: =H97/Assumptions!$G$16 -> 1053293.5 | I100: =I97/Assumptions!$G$16 -> 1053293.5 | ... AE100: =AE97/Assumptions!$G$16 -> 808330.22
A101: Remaining | B101: =B97-B100 -> 15675.798 | C101: =C97-C100 -> 31351.595 | D101: =D97-D100 -> 62703.19 | E101: =E97-E100 -> 102261.51 | F101: =F97-F100 -> 102261.51 | G101: =G97-G100 -> 102261.51 | H101: =H97-H100 -> 105329.35 | I101: =I97-I100 -> 105329.35 | ... AE101: =AE97-AE100 -> 80833.022
A103: A Bond
A104: Cash Flow | B104: =B100 -> 156757.98 | C104: =C100 -> 313515.95 | D104: =D100 -> 627031.9 | E104: =E100 -> 1022615.1 | F104: =F100 -> 1022615.1 | G104: =G100 -> 1022615.1 | H104: =H100 -> 1053293.5 | I104: =I100 -> 1053293.5 | ... AE104: =AE100 -> 808330.22
A105: Reserve | B105: 0 | C105: 0 | D105: 0 | E105: 0 | F105: 0 | G105: 0 | H105: 0 | I105: 0 | J105: 0 | K105: 0 | L105: 0 | M105: 0 | N105: 0 | O105: 0 | P105: 0 | Q105: 0 | R105: 0 | S105: 0 | T105: 0 | U105: 0 | V105: 0 | W105: 0 | X105: 0 | Y105: 0 | Z105: 0 | AA105: 0 | AB105: 0 | AC105: 0 | AD105: 0
A106: B Bond
A107: Cash Flow | B107: =B101 -> 15675.798 | C107: =C101 -> 31351.595 | D107: =D101 -> 62703.19 | E107: =E101 -> 102261.51 | F107: =F101 -> 102261.51 | G107: =G101 -> 102261.51 | H107: =H101 -> 105329.35 | I107: =I101 -> 105329.35 | ... AE107: =AE101 -> 80833.022
...

Sheet Revenue Summary
A1: Index Year | B1: 1 | C1: =B1+1 -> 2 | D1: =C1+1 -> 3 | E1: =D1+1 -> 4 | F1: =E1+1 -> 5 | G1: =F1+1 -> 6 | H1: =G1+1 -> 7 | I1: =H1+1 -> 8 | J1: =I1+1 -> 9 | ... AE1: =AD1+1 -> 30
A2: Tax Year | B2: =Calculations!B1 -> 2020 | C2: =B2+1 -> 2021 | D2: =C2+1 -> 2022 | E2: =D2+1 -> 2023 | F2: =E2+1 -> 2024 | G2: =F2+1 -> 2025 | H2: =G2+1 -> 2026 | I2: =H2+1 -> 2027 | J2: =I2+1 -> 2028 | ... AE2: =AD2+1 -> 2049
A3: Collection Year | B3: =Calculations!B2 -> 2021 | C3: =Calculations!C2 -> 2022 | D3: =Calculations!D2 -> 2023 | E3: =Calculations!E2 -> 2024 | F3: =Calculations!F2 -> 2025 | G3: =Calculations!G2 -> 2026 | H3: =Calculations!H2 -> 2027 | I3: =Calculations!I2 -> 2028 | ... AE3: =Calculations!AE2 -> 2050
A4: MINIMUM SERVICE PAYMENTS ON PHASE 1 - CONSTRUCTION
A5: =Calculations!A93 -> Apartments | B5: =Calculations!B24 -> 153901.28 | C5: =Calculations!C24 -> 307802.57 | D5: =Calculations!D24 -> 615605.14 | E5: =Calculations!E24 -> 652541.44 | F5: =Calculations!F24 -> 652541.44 | G5: =Calculations!G24 -> 652541.44 | H5: =Calculations!H24 -> 672117.69 | I5: =Calculations!I24 -> 672117.69 | ... AE5: =Calculations!AE24 -> 486564.39
A6: =Calculations!A94 -> Office | B6: =Calculations!B45 -> 18532.49 | C6: =Calculations!C45 -> 37064.98 | D6: =Calculations!D45 -> 74129.96 | E6: =Calculations!E45 -> 78577.758 | F6: =Calculations!F45 -> 78577.758 | G6: =Calculations!G45 -> 78577.758 | H6: =Calculations!H45 -> 80935.09 | I6: =Calculations!I45 -> 80935.09 | ... AE6: =Calculations!AE45 -> 86744.23
A7: =Calculations!A95 -> Single-Family Homes | B7: =Calculations!B67 -> 0 | C7: =Calculations!C67 -> 0 | D7: =Calculations!D67 -> 0 | E7: =Calculations!E67 -> 132901.92 | F7: =Calculations!F67 -> 132901.92 | G7: =Calculations!G67 -> 132901.92 | H7: =Calculations!H67 -> 136888.98 | I7: =Calculations!I67 -> 136888.98 | ... AE7: =Calculations!AE67 -> 106608
A8: =Calculations!A96 -> Condos | B8: =Calculations!B89 -> 0 | C8: =Calculations!C89 -> 0 | D8: =Calculations!D89 -> 0 | E8: =Calculations!E89 -> 260855.44 | F8: =Calculations!F89 -> 260855.44 | G8: =Calculations!G89 -> 260855.44 | H8: =Calculations!H89 -> 268681.1 | I8: =Calculations!I89 -> 268681.1 | ... AE8: =Calculations!AE89 -> 209246.62
A9: TOTAL MINIMUM SERVICE PAYMENTS | B9: =SUM(B5:B8) -> 172433.77 | C9: =SUM(C5:C8) -> 344867.55 | D9: =SUM(D5:D8) -> 689735.1 | E9: =SUM(E5:E8) -> 1124876.6 | F9: =SUM(F5:F8) -> 1124876.6 | G9: =SUM(G5:G8) -> 1124876.6 | H9: =SUM(H5:H8) -> 1158622.9 | I9: =SUM(I5:I8) -> 1158622.9 | ... AE9: =SUM(AE5:AE8) -> 889163.25
A11: Debt Coverage
A12: Cash Flow | B12: =B9/Assumptions!$G$16 -> 156757.98 | C12: =C9/Assumptions!$G$16 -> 313515.95 | D12: =D9/Assumptions!$G$16 -> 627031.9 | E12: =E9/Assumptions!$G$16 -> 1022615.1 | F12: =F9/Assumptions!$G$16 -> 1022615.1 | G12: =G9/Assumptions!$G$16 -> 1022615.1 | H12: =H9/Assumptions!$G$16 -> 1053293.5 | I12: =I9/Assumptions!$G$16 -> 1053293.5 | ... AE12: =AE9/Assumptions!$G$16 -> 808330.22
A13: Remaining | B13: =B9-B12 -> 15675.798 | C13: =C9-C12 -> 31351.595 | D13: =D9-D12 -> 62703.19 | E13: =E9-E12 -> 102261.51 | F13: =F9-F12 -> 102261.51 | G13: =G9-G12 -> 102261.51 | H13: =H9-H12 -> 105329.35 | I13: =I9-I12 -> 105329.35 | ... AE13: =AE9-AE12 -> 80833.022
A15: A Bond
A16: Cash Flow | B16: =B12 -> 156757.98 | C16: =C12 -> 313515.95 | D16: =D12 -> 627031.9 | E16: =E12 -> 1022615.1 | F16: =F12 -> 1022615.1 | G16: =G12 -> 1022615.1 | H16: =H12 -> 1053293.5 | I16: =I12 -> 1053293.5 | ... AE16: =AE12 -> 808330.22
A17: Reserve | B17: 0 | C17: 0 | D17: 0 | E17: 0 | F17: 0 | G17: 0 | H17: 0 | I17: 0 | J17: 0 | K17: 0 | L17: 0 | M17: 0 | N17: 0 | O17: 0 | P17: 0 | Q17: 0 | R17: 0 | S17: 0 | T17: 0 | U17: 0 | V17: 0 | W17: 0 | X17: 0 | Y17: 0 | Z17: 0 | AA17: 0 | AB17: 0 | AC17: 0 | AD17: 0
A18: Surplus
A19: Excess from A (Debt Coverage) | B19: =B13 -> 15675.798 | C19: =C13 -> 31351.595 | D19: =D13 -> 62703.19 | E19: =E13 -> 102261.51 | F19: =F13 -> 102261.51 | G19: =G13 -> 102261.51 | H19: =H13 -> 105329.35 | I19: =I13 -> 105329.35 | ... AE19: =AE13 -> 80833.022
